Workbook

Sheet Artikelstamm
A1: STAMMDATEN | K1: BUCHHALTUNG | N1: PREIS | P1: VERMARKTUNG | U1: VERKAUF | Y1: KAUFMÄNNISCH
A2: ArtNr | B2: Bezeichnung | C2: Beschreibung | D2: Kategorie | E2: Raum | F2: Menge | G2: Verkauft_Menge | H2: Restmenge | I2: Einheit | J2: Zustand | K2: Anschaffungsjahr | L2: Anlagennr | M2: Anschaffungswert_netto | N2: Preis_netto | O2: Preisbasis | P2: Versand | Q2: Foto | R2: Status | S2: Kanal | T2: Reserviert_für | U2: Verkaufspreis_netto | V2: Umsatz_netto | W2: Verkaufsdatum | X2: Käufer | Y2: Rechnungsnr | Z2: Zahlung | AA2: Zahlart | AB2: Abholtermin | AC2: Bemerkung
A3: K-001 | B3: Garderobenbank mit Hakenleiste | C3: Buche massiv, 6 Plätze, B 120 x H 140 x T 35 cm, Sitzbank mit Schuhablage | D3: Möbel | E3: Flur EG | F3: 12 | H3: =F3-IF(G3="",0,G3) | I3: Stück | J3: gut | K3: 2009 | L3: AV-0112 | M3: 340 | N3: 85 | O3: Fix | P3: nur Abholung | Q3: K-001.jpg | R3: verfügbar | S3: Klinik | V3: =IF(G3="","",G3*U3) | AC3: 2 Stück mit leichten Kratzern
A4: K-002 | B4: Kindertisch trapezförmig | C4: Buche, 120 x 60 cm, Höhe 53 cm, kombinierbar zu Sechseck | D4: Möbel | E4: Gruppenraum 1-3 | F4: 18 | H4: =F4-IF(G4="",0,G4) | I4: Stück | J4: gut | K4: 2010 | L4: AV-0118 | M4: 180 | N4: 45 | O4: Fix | P4: nur Abholung | Q4: K-002.jpg | R4: verfügbar | S4: Klinik | V4: =IF(G4="","",G4*U4)
A5: K-003 | B5: Kinderstuhl Holz | C5: Buche, Sitzhöhe 34 cm, stapelbar | D5: Möbel | E5: Gruppenraum 1-3 | F5: 64 | H5: =F5-IF(G5="",0,G5) | I5: Stück | J5: gebraucht | K5: 2010 | L5: AV-0119 | M5: 48 | N5: 12 | O5: Fix | P5: Versand möglich | Q5: K-003.jpg | R5: verfügbar | S5: Klinik | V5: =IF(G5="","",G5*U5) | AC5: Mengenrabatt ab 20 Stück möglich
A6: K-004 | B6: Rollcontainer Materialwagen | C6: Weiß, 4 Schubladen, abschließbar, auf Rollen, B 40 x H 60 cm | D6: Möbel | E6: Gruppenraum 2 | F6: 6 | H6: =F6-IF(G6="",0,G6) | I6: Stück | J6: gut | K6: 2014 | L6: AV-0231 | M6: 210 | N6: 60 | O6: Fix | P6: Versand möglich | Q6: K-004.jpg | R6: reserviert | S6: Klinik | T6: Klinikum Musterstadt | V6: =IF(G6="","",G6*U6) | AC6: Reservierung bis 30.09.
A7: K-005 | B7: Wickelkommode mit Aufstiegstreppe | C7: Mit ausziehbarer Treppe, Wickelauflage, 2 Ablagefächer, B 100 x H 100 cm | D7: Möbel | E7: Waschraum | F7: 2 | H7: =F7-IF(G7="",0,G7) | I7: Stück | J7: gut | K7: 2015 | L7: AV-0288 | M7: 890 | N7: 320 | O7: VHB | P7: nur Abholung | Q7: K-005.jpg | R7: verfügbar | S7: Klinik | V7: =IF(G7="","",G7*U7) | AC7: Für Kinderstation interessant
A8: K-006 | B8: Ruheliege stapelbar | C8: Stapelliege, Metallrahmen mit Netzbespannung, 130 x 60 cm | D8: Möbel | E8: Schlafraum | F8: 20 | H8: =F8-IF(G8="",0,G8) | I8: Stück | J8: gebraucht | K8: 2011 | L8: GWG-0421 | M8: 65 | N8: 18 | O8: Fix | P8: Versand möglich | Q8: K-006.jpg | R8: verfügbar | S8: Kleinanzeigen | V8: =IF(G8="","",G8*U8)
A9: K-007 | B9: Spielteppich groß | C9: 200 x 300 cm, Motiv Straßenverkehr, gereinigt | D9: Spielmaterial | E9: Gruppenraum 1 | F9: 3 | H9: =F9-IF(G9="",0,G9) | I9: Stück | J9: gebraucht | K9: 2016 | N9: 35 | O9: VHB | P9: Versand möglich | Q9: K-007.jpg | R9: verfügbar | S9: Klinik | V9: =IF(G9="","",G9*U9)
A10: K-008 | B10: Karton Acrylfarben | C10: ca. 40 Flaschen à 500 ml, verschiedene Farben, ungeöffnet | D10: Verbrauchsmaterial | E10: Lager | F10: 3 | H10: =F10-IF(G10="",0,G10) | I10: Karton | J10: neuwertig | K10: 2024 | N10: 95 | O10: Fix | P10: Versand möglich | Q10: K-008.jpg | R10: verfügbar | S10: Klinik | V10: =IF(G10="","",G10*U10) | AC10: Haltbarkeit geprüft
A11: K-009 | B11: Karton gemischtes Spielzeug | C11: Bausteine, Fahrzeuge, Puzzles, Steckspiele - gereinigt, vollständig geprüfte Sets | D11: Spielmaterial | E11: Lager | F11: 12 | H11: =F11-IF(G11="",0,G11) | I11: Karton | J11: gebraucht | N11: 15 | O11: VHB | P11: Versand möglich | Q11: K-009.jpg | R11: verfügbar | S11: Klinik | V11: =IF(G11="","",G11*U11) | AC11: Inhalt je Karton leicht unterschiedlich
A12: K-010 | B12: Gewerbespülmaschine Hobart | C12: Untertischgerät, Bj. 2016, gewartet 03/2025, 400 V | D12: Küchentechnik | E12: Küche | F12: 1 | H12: =F12-IF(G12="",0,G12) | I12: Stück | J12: gut | K12: 2016 | L12: AV-0301 | M12: 3200 | N12: 1450 | O12: VHB | P12: nur Abholung | Q12: K-010.jpg | R12: verfügbar | S12: Klinik | V12: =IF(G12="","",G12*U12) | AC12: Elektroanschluss durch Fachbetrieb
A13: K-011 | B13: Edelstahl-Arbeitstisch | C13: 180 x 70 cm, mit Zwischenboden, höhenverstellbare Füße | D13: Küchentechnik | E13: Küche | F13: 3 | H13: =F13-IF(G13="",0,G13) | I13: Stück | J13: gut | K13: 2016 | L13: AV-0302 | M13: 620 | N13: 180 | O13: Fix | P13: nur Abholung | Q13: K-011.jpg | R13: verfügbar | S13: Klinik | V13: =IF(G13="","",G13*U13)
A14: K-012 | B14: Aktenschrank abschließbar | C14: Stahl, 4 Ordnerhöhen, grau, B 92 x H 195 cm | D14: Büro | E14: Büro Leitung | F14: 4 | G14: 2 | H14: =F14-IF(G14="",0,G14) | I14: Stück | J14: gut | K14: 2012 | L14: AV-0155 | M14: 390 | N14: 95 | O14: Fix | P14: nur Abholung | Q14: K-012.jpg | R14: verkauft | S14: Direkt | U14: 95 | V14: =IF(G14="","",G14*U14) | W14: 08.09.2026 | X14: Praxis Dr. Berger | Y14: RE-2026-0014 | Z14: bezahlt | AA14: Überweisung | AB14: 08.09.2026
A15: K-013 | B15: Schreibtisch höhenverstellbar | C15: 160 x 80 cm, Kurbelverstellung, Ahorn | D15: Büro | E15: Büro Leitung | F15: 2 | G15: 1 | H15: =F15-IF(G15="",0,G15) | I15: Stück | J15: gut | K15: 2018 | L15: AV-0344 | M15: 450 | N15: 150 | O15: VHB | P15: nur Abholung | Q15: K-013.jpg | R15: verkauft | S15: Kleinanzeigen | U15: 140 | V15: =IF(G15="","",G15*U15) | W15: 10.09.2026 | X15: Herr Schmidt (privat) | Y15: RE-2026-0015 | Z15: offen | AA15: bar | AB15: 17.09.2026 | AC15: Abholung vereinbart
A16: K-014 | B16: Sonnensegel Außenbereich | C16: 5 x 5 m, mit 4 Bodenhülsen und Spannseilen | D16: Außenbereich | E16: Garten | F16: 1 | H16: =F16-IF(G16="",0,G16) | I16: Stück | J16: gebraucht | K16: 2019 | L16: GWG-0512 | M16: 280 | N16: 90 | O16: VHB | P16: nur Abholung | Q16: K-014.jpg | R16: verfügbar | S16: Kleinanzeigen | V16: =IF(G16="","",G16*U16) | AC16: Demontage durch Käufer
A17: K-015 | B17: Musikinstrumente-Set Orff | C17: Xylophone, Trommeln, Rasseln, Klangstäbe - im Holzwagen | D17: Musik | E17: Bewegungsraum | F17: 1 | G17: 1 | H17: =F17-IF(G17="",0,G17) | I17: Set | J17: gut | K17: 2013 | L17: AV-0201 | M17: 1100 | N17: 380 | O17: VHB | P17: nur Abholung | Q17: K-015.jpg | R17: verkauft | S17: Direkt | U17: 380 | V17: =IF(G17="","",G17*U17) | W17: 05.09.2026 | X17: Kita Sonnenschein e.V. | Y17: RE-2026-0012 | Z17: bezahlt | AA17: Überweisung | AB17: 05.09.2026
A18: K-016 | B18: Laptop Lenovo ThinkPad | C18: i5, 8 GB RAM, 256 GB SSD, Bj. 2020, ohne Betriebssystem, Datenträger gelöscht | D18: IT | E18: Büro Leitung | F18: 2 | H18: =F18-IF(G18="",0,G18) | I18: Stück | J18: gebraucht | K18: 2020 | L18: AV-0388 | M18: 780 | N18: 210 | O18: Fix | P18: Versand möglich | Q18: K-016.jpg | R18: verfügbar | S18: eBay | V18: =IF(G18="","",G18*U18) | AC18: Datenlöschung protokolliert

Sheet Verkaufsübersicht
A1: Verkaufsübersicht – alle Werte rechnen automatisch aus dem Artikelstamm
A2: Es muss nichts von Hand gepflegt werden. Wer im Artikelstamm einen Verkauf einträgt, sieht ihn sofort hier.
A4: Bestand
A5: Artikelpositionen gesamt | B5: =COUNTA(Artikelstamm!$A$3:$A$18)
A6: davon verfügbar | B6: =COUNTIF(Artikelstamm!$R$3:$R$18,"verfügbar")
A7: davon reserviert | B7: =COUNTIF(Artikelstamm!$R$3:$R$18,"reserviert")
A8: davon verkauft | B8: =COUNTIF(Artikelstamm!$R$3:$R$18,"verkauft")
A9: Einheiten noch im Bestand | B9: =SUM(Artikelstamm!$H$3:$H$18)
A10: Restbestand zu Wunschpreisen (netto) | B10: =SUMPRODUCT(Artikelstamm!$H$3:$H$18,Artikelstamm!$N$3:$N$18)
A12: Erlöse
A13: Verkaufte Einheiten | B13: =SUM(Artikelstamm!$G$3:$G$18)
A14: Umsatz netto | B14: =SUMPRODUCT(Artikelstamm!$G$3:$G$18,Artikelstamm!$U$3:$U$18)
A15: zzgl. Umsatzsteuer 19 % | B15: =B14*0.19
A16: Umsatz brutto | B16: =B14+B15
A17: davon bereits bezahlt (netto) | B17: =SUMPRODUCT((Artikelstamm!$Z$3:$Z$18="bezahlt")*Artikelstamm!$G$3:$G$18*Artikelstamm!$U$3:$U$18)
A18: noch offen (netto) | B18: =B14-B17
A20: To-do
A21: Rechnungen noch zu schreiben | B21: =COUNTIFS(Artikelstamm!$R$3:$R$18,"verkauft",Artikelstamm!$Y$3:$Y$18,"")
A22: Rechnungen offen (unbezahlt) | B22: =COUNTIFS(Artikelstamm!$R$3:$R$18,"verkauft",Artikelstamm!$Z$3:$Z$18,"offen")
A23: Reservierungen ohne Abholtermin | B23: =COUNTIFS(Artikelstamm!$R$3:$R$18,"reserviert",Artikelstamm!$AB$3:$AB$18,"")
A24: Artikel ohne Preis | B24: =COUNTIFS(Artikelstamm!$N$3:$N$18,"")
A25: Artikel ohne Foto | B25: =COUNTIFS(Artikelstamm!$Q$3:$Q$18,"")
A27: Nach Kategorie
A28: Kategorie | B28: Positionen | C28: Umsatz netto | D28: Restwert netto
A29: Außenbereich | B29: =COUNTIF(Artikelstamm!$D$3:$D$18,$A29) | C29: =SUMPRODUCT((Artikelstamm!$D$3:$D$18=$A29)*Artikelstamm!$G$3:$G$18*Artikelstamm!$U$3:$U$18) | D29: =SUMPRODUCT((Artikelstamm!$D$3:$D$18=$A29)*Artikelstamm!$H$3:$H$18*Artikelstamm!$N$3:$N$18)
A30: Büro | B30: =COUNTIF(Artikelstamm!$D$3:$D$18,$A30) | C30: =SUMPRODUCT((Artikelstamm!$D$3:$D$18=$A30)*Artikelstamm!$G$3:$G$18*Artikelstamm!$U$3:$U$18) | D30: =SUMPRODUCT((Artikelstamm!$D$3:$D$18=$A30)*Artikelstamm!$H$3:$H$18*Artikelstamm!$N$3:$N$18)
A31: IT | B31: =COUNTIF(Artikelstamm!$D$3:$D$18,$A31) | C31: =SUMPRODUCT((Artikelstamm!$D$3:$D$18=$A31)*Artikelstamm!$G$3:$G$18*Artikelstamm!$U$3:$U$18) | D31: =SUMPRODUCT((Artikelstamm!$D$3:$D$18=$A31)*Artikelstamm!$H$3:$H$18*Artikelstamm!$N$3:$N$18)
A32: Küchentechnik | B32: =COUNTIF(Artikelstamm!$D$3:$D$18,$A32) | C32: =SUMPRODUCT((Artikelstamm!$D$3:$D$18=$A32)*Artikelstamm!$G$3:$G$18*Artikelstamm!$U$3:$U$18) | D32: =SUMPRODUCT((Artikelstamm!$D$3:$D$18=$A32)*Artikelstamm!$H$3:$H$18*Artikelstamm!$N$3:$N$18)
A33: Musik | B33: =COUNTIF(Artikelstamm!$D$3:$D$18,$A33) | C33: =SUMPRODUCT((Artikelstamm!$D$3:$D$18=$A33)*Artikelstamm!$G$3:$G$18*Artikelstamm!$U$3:$U$18) | D33: =SUMPRODUCT((Artikelstamm!$D$3:$D$18=$A33)*Artikelstamm!$H$3:$H$18*Artikelstamm!$N$3:$N$18)
A34: Möbel | B34: =COUNTIF(Artikelstamm!$D$3:$D$18,$A34) | C34: =SUMPRODUCT((Artikelstamm!$D$3:$D$18=$A34)*Artikelstamm!$G$3:$G$18*Artikelstamm!$U$3:$U$18) | D34: =SUMPRODUCT((Artikelstamm!$D$3:$D$18=$A34)*Artikelstamm!$H$3:$H$18*Artikelstamm!$N$3:$N$18)
A35: Spielmaterial | B35: =COUNTIF(Artikelstamm!$D$3:$D$18,$A35) | C35: =SUMPRODUCT((Artikelstamm!$D$3:$D$18=$A35)*Artikelstamm!$G$3:$G$18*Artikelstamm!$U$3:$U$18) | D35: =SUMPRODUCT((Artikelstamm!$D$3:$D$18=$A35)*Artikelstamm!$H$3:$H$18*Artikelstamm!$N$3:$N$18)
A36: Verbrauchsmaterial | B36: =COUNTIF(Artikelstamm!$D$3:$D$18,$A36) | C36: =SUMPRODUCT((Artikelstamm!$D$3:$D$18=$A36)*Artikelstamm!$G$3:$G$18*Artikelstamm!$U$3:$U$18) | D36: =SUMPRODUCT((Artikelstamm!$D$3:$D$18=$A36)*Artikelstamm!$H$3:$H$18*Artikelstamm!$N$3:$N$18)
A37: Summe | B37: =SUM(B29:B36) | C37: =SUM(C29:C36) | D37: =SUM(D29:D36)
A39: Nach Verkaufskanal
A40: Kanal | B40: Positionen | C40: Umsatz netto
A41: Direkt | B41: =COUNTIF(Artikelstamm!$S$3:$S$18,$A41) | C41: =SUMPRODUCT((Artikelstamm!$S$3:$S$18=$A41)*Artikelstamm!$G$3:$G$18*Artikelstamm!$U$3:$U$18)
A42: Kleinanzeigen | B42: =COUNTIF(Artikelstamm!$S$3:$S$18,$A42) | C42: =SUMPRODUCT((Artikelstamm!$S$3:$S$18=$A42)*Artikelstamm!$G$3:$G$18*Artikelstamm!$U$3:$U$18)
A43: Klinik | B43: =COUNTIF(Artikelstamm!$S$3:$S$18,$A43) | C43: =SUMPRODUCT((Artikelstamm!$S$3:$S$18=$A43)*Artikelstamm!$G$3:$G$18*Artikelstamm!$U$3:$U$18)
A44: eBay | B44: =COUNTIF(Artikelstamm!$S$3:$S$18,$A44) | C44: =SUMPRODUCT((Artikelstamm!$S$3:$S$18=$A44)*Artikelstamm!$G$3:$G$18*Artikelstamm!$U$3:$U$18)

Sheet Legende
A1: Legende / Ausfüllhilfe
A3: Gelbe Felder | B3: Das sind die Felder, die im Tagesgeschäft gepflegt werden. Alles andere bleibt meist unverändert.
A4: ArtNr | B4: Eindeutige Nummer. Kommt auch als Etikett an den Artikel im Haus – so passen Liste und Realität zusammen.
A5: Menge | B5: Ursprünglich vorhandene Stückzahl. Bleibt stehen, auch wenn verkauft wird.
A6: Verkauft_Menge / Restmenge | B6: Restmenge rechnet sich selbst aus (Menge minus verkaufte Menge). Nicht überschreiben.
A7: Einheit | B7: Stück, Karton, Set, Palette, Konvolut. Für 'ein Karton Acrylfarben' also Einheit = Karton.
A8: Anlagennr | B8: Verweis auf Anlagenverzeichnis bzw. GWG-Liste – damit der Steuerberater den Abgang zuordnen kann.
A9: Preis_netto | B9: Verkaufspreis OHNE Umsatzsteuer, pro Einheit. Gegenüber Firmen wird netto angeboten, gegenüber Privatleuten brutto ausgewiesen.
A10: Preisbasis | B10: Fix = Festpreis, VHB = Verhandlungsbasis.
A11: Status | B11: verfügbar / reserviert / verkauft / gespendet / entsorgt. Steuert, was im Online-Katalog angezeigt wird.
A12: Kanal | B12: Wo der Artikel angeboten wird: Klinik, Kleinanzeigen, eBay, Direkt, Händler.
A13: Umsatz_netto | B13: Rechnet sich selbst aus (verkaufte Menge × Verkaufspreis). Nicht überschreiben.
A14: Zahlung | B14: offen / bezahlt / teilbezahlt. Bar bezahlte Beträge zusätzlich ins Kassenbuch eintragen (GoBD).
... A16: Wichtig | B16: Diese Datei ist die einzige Quelle der Wahrheit. Aus ihr entstehen Klinik-Angebot, Online-Katalog, eBay-/Kleinanzeigen-Inserate und die Zahlen für die Buchhaltung.
