Workbook

Sheet Anleitung
A1: Artikelverwaltung Betriebsauflösung – Kurzanleitung
A2: Diese Datei liegt in OneDrive und ist die einzige Quelle der Wahrheit. Bitte immer direkt hier arbeiten – nicht herunterladen, bearbeiten und wieder hochladen.
A4: Die Blätter
A5: Artikelstamm | B5: Alle Artikel. Hier wird gepflegt. Grau hinterlegte Spalten sind die Felder zum Ausfüllen, alles andere rechnet sich selbst oder bleibt stehen.
A6: Verkaufsübersicht | B6: Reines Auswertungsblatt. Umsatz, offene Rechnungen, Restbestand – rechnet automatisch. Hier nichts eintragen.
A7: Kasse | B7: Barverkäufe je Tag für das Kassenbuch. Pflicht bei einer GmbH (GoBD).
A9: Die wichtigsten Regeln
A10: Ein Artikel verkauft | B10: Status auf „verkauft“, Verkaufspreis, Verkaufte Menge, Käufer und Datum eintragen. Der Rest rechnet sich.
A11: Reservierung | B11: Status auf „reserviert“, Name und Abholtermin eintragen. Ohne Abholtermin keine Reservierung – sonst blockiert die Ware.
A12: Restmenge | B12: Rechnet sich aus Menge minus verkaufter Menge. Nicht überschreiben.
A13: Preise | B13: Endpreis pro Einheit. Die Spalte heißt weiter Preis_netto, es wird aber keine Umsatzsteuer aufgeschlagen: steuerfreie Lieferung gemäß § 4 Nr. 28 UStG.
A14: Wertklasse | B14: A = Wertträger, einzeln vermarkten · B = Einzelposition im Katalog · C = Kleinteil, geht in den Verkaufstag.
A15: Barzahlung | B15: Seit Oktober 2026 wird nur überwiesen. Falls doch einmal bar bezahlt wird: zusätzlich im Blatt „Kasse“ erfassen.
A16: Anlagennummer | B16: Wenn bekannt eintragen – der Steuerberater braucht sie für den Anlagenabgang.
A18: Hinweise zu den Preisen | B18: Alle Preise in dieser Datei sind Schätzwerte auf Basis der Fotos. Sie sind zur Überarbeitung gedacht.
A19: Preis_geprüft | B19: „offen“ = Preis ist noch geschätzt und muss kontrolliert werden (dunkelgrau hinterlegt). Nach der Kontrolle „ok“ eintragen. Filter auf „offen“ zeigt die Prüfliste. Artikel mit „offen“ gehen nicht in den Webkatalog.
A20: Markenware | B20: Vitra, Stokke, USM Haller und Kartell sind dort vermerkt, wo die Marke am Stück belegt ist. Für diese Stücke gibt es einen eigenen Gebrauchtmarkt mit Fachhändlern – dort sind höhere Preise erzielbar als im Sammelangebot.
A21: Kunst | B21: Die Acrylbilder sind Eigenarbeiten einer Privatperson, die Schwarzwald-Trachtenmotive sind Kaufware. Beides ist in der Beschreibung vermerkt.
A23: Für die Prüfrunde
A24: So geht es am schnellsten | B24: Von oben nach unten durchgehen: Bild und Bezeichnung ansehen, Preis_netto prüfen oder überschreiben, weiter. Die Räume stehen zusammen, es ist also ein Rundgang durchs Haus.
A25: Was angefasst wird | B25: Nur vier Spalten: Preis_netto, Anlagennr, Anschaffungswert_netto und – falls etwas gar nicht angeboten werden soll – Im_Katalog auf „nein“. Alles andere kann so bleiben.
A26: Was man lassen sollte | B26: Keine Zeilen löschen. Eine fehlende Zeile wird beim Einlesen als „entfällt“ gewertet und verschwindet aus dem Katalog. Soll etwas raus, bitte Aktiv auf „entfällt“ setzen.
A27: Das Bild in Spalte A | B27: Jede Zeile zeigt links das Foto des Artikels – dasselbe Bild, das später im Webkatalog steht. So lässt sich der Preis direkt am Stück beurteilen, ohne die Fotos daneben zu öffnen.
A28: Filtern statt Sortieren | B28: Zum Eingrenzen bitte den Filter in Zeile 2 benutzen (z. B. nur ein Raum). Sortieren ist in diesem Blatt gesperrt: Excel ordnet dabei zwar die Zeilen um, lässt die Bilder aber stehen – danach stünde jedes Foto beim falschen Artikel.
A29: Zugeklappte Spalten | B29: Zweimal sind Spalten als Gruppe zugeklappt: die Detailangaben (Kategorie bis Maße) und ganz rechts die Verkaufsspalten. So steht Preis_netto gleich neben Bild und Bezeichnung. Das Plus über der Spaltenleiste klappt sie auf.
A30: Formeln | B30: Restmenge, Positionswert und Umsatz rechnen sich selbst und sind gegen Überschreiben geschützt.

Sheet Artikelstamm
A1: STAMMDATEN | Q1: BUCHHALTUNG | S1: PREIS | W1: VERMARKTUNG | AE1: VERKAUF | AI1: KAUFMÄNNISCH | AM1: NOTIZEN
A2: Bild | B2: ArtNr | C2: Raumcode | D2: Raum | E2: Bezeichnung | F2: Menge | G2: Beschreibung | H2: Kategorie | I2: Weitere_ArtNr | J2: Wertklasse | K2: Einheit | L2: Maße | M2: Zustand | N2: Verkauft_Menge | O2: Restmenge | P2: Aktiv | Q2: Anlagennr | R2: Anschaffungswert_netto | S2: Preis_netto | T2: Preisbasis | U2: Preis_geprüft | V2: Positionswert_netto | W2: Versand | X2: Foto | Y2: Im_Katalog | Z2: Status | AA2: Marke | AB2: Bündel | AC2: Kanal | AD2: Reserviert_für | AE2: Verkaufspreis_netto | AF2: Umsatz_netto | AG2: Verkaufsdatum | AH2: Käufer | AI2: Rechnungsnr | AJ2: Zahlung | AK2: Zahlart | AL2: Abholtermin | AM2: Mengenhinweis | AN2: Bemerkung
B3: BA04-01 | C3: BA04 | D3: Gruppenraum | E3: Rattankörbe 8 Stück | F3: 1 | G3: Rattankörbe 8 Stück | H3: Deko | J3: C | K3: Set | M3: gebraucht | O3: =F3-IF(N3="",0,N3) | P3: ja | S3: 40 | T3: Fix | U3: ok | V3: =O3*S3 | W3: nur Abholung | X3: F-062 | Y3: ja | Z3: reserviert | AC3: Webkatalog | AD3: Ann - Katrin Fischer | AF3: =IF(N3="","",N3*AE3) | AL3: 22.10.2026 15:00 | AM3: 1 Set Körbe. Ohne Regal | AN3: Notiz aus der ersten Liste: 1 Regal mit 6 Körben im Bild · Webkatalog: Barzahlung
B4: BA04-02 | C4: BA04 | D4: Gruppenraum | E4: Holzkiste Obstkistenoptik | F4: 4 | G4: Alte Holzkiste, unbehandelt, als Aufbewahrung | H4: Deko | J4: C | K4: Stück | M4: gebraucht | O4: =F4-IF(N4="",0,N4) | P4: entfällt | S4: 15 | T4: Fix | V4: =O4*S4 | W4: nur Abholung | X4: F-063 | Y4: ja | Z4: verfügbar | AF4: =IF(N4="","",N4*AE4)
B5: BA08-01 | C5: BA08 | D5: Atelier | E5: Konvolut Mal- und Bastelfarben | F5: 1 | G5: Creall Fingerpaint: jeweils 1 angefangene Flasche braun, gelb, hellrosa, dunkelrot, violett, weiß und hellblau; jeweils 1 ungeöffnete Flasche schwarz, blau, dunkelblau, hellgrün und hellblau; Insgesamt Plakatfarbe (Moje Bambino) 2 ungeöffnete Flaschen braun, weiß, violett und schwarz, 1 ungeöffnete Flasche orange, grün, dunkelblau und gelb, 3 ungeöffnete Flaschen hellrosa und rot sowie jeweils ca. 1/2 Flasche gelb, hellrosa, violett, jeweils angebraucht ( nur geringe Menge entnommen) 2x blau, 2x dunkelblau 1x hellgrün und 1x orange | H5: Verbrauchsmaterial | J5: C | K5: Konvolut | M5: gebraucht | O5: =F5-IF(N5="",0,N5) | P5: ja | S5: 120 | T5: Fix | U5: ok | V5: =O5*S5 | W5: nur Abholung | X5: F-065 | Y5: ja | Z5: verfügbar | AF5: =IF(N5="","",N5*AE5) | AM5: div. Farben der Farbpalette, teilweise bereits angebraucht
B6: BA08-02 | C6: BA08 | D6: Atelier | E6: Acrylfarben-Sortiment | F6: 1 | G6: Karton mit Acrylfarben 2xgrau, 1x blau, 2x dunkelbraun, 1x grün, 1x gelb (bereits angebraucht), 1x hellgrün 2x rot, 3x hellbraun, 1x türkis, 2x oliv, 1x orange, 3x phtalo grün, 4x braun Herstellungsdatum: 10/24; bis auf eine Tube sind alle Farben unbenutzt | H6: Verbrauchsmaterial | J6: C | K6: Konvolut | M6: neuwertig | O6: =F6-IF(N6="",0,N6) | P6: entfällt | S6: 48 | T6: Fix | U6: ok | V6: =O6*S6 | W6: nur Abholung | X6: F-546 | Y6: ja | Z6: verfügbar | AF6: =IF(N6="","",N6*AE6) | AN6: 13.10.2026: auf Wunsch der Nutzerin aus dem Katalog (entfällt).
B7: BA08-03 | C7: BA08 | D7: Atelier | E7: Konvolut Bastelmaterial | F7: 1 | G7: 1 Karton Bastelmaterial bestehend aus diverse Kunststoff-Perlen, Bänder, Glitzer, Holzperlen, Bügelperlen, Schnüre alles in verschiedenen Farben und Formen; Basteldraht, Streuglitzer,Sand etc. | H7: Verbrauchsmaterial | J7: C | K7: Konvolut | M7: gut | N7: 1 | O7: =F7-IF(N7="",0,N7) | P7: ja | S7: 50 | T7: Fix | U7: ok | V7: =O7*S7 | W7: nur Abholung | X7: F-070 | Y7: ja | Z7: verkauft | AC7: Webkatalog | AE7: 50 | AF7: =IF(N7="","",N7*AE7) | AG7: 14.10.2026 | AH7: Maren Kipp | AI7: 4000114 | AJ7: bezahlt | AL7: 09.11.2026 08:00
B8: BA08-04 | C8: BA08 | D8: Atelier | E8: buntes Tonpapier | F8: 1 | G8: buntes Tonpapier -70x50cm 1x schwarz, 5x weiß, 4x rot; 9x hochrot, 11x gelb, 6x orange, 8x lila, 4x hellblau, 5x dunkelblau 5x blau, 12x hellgrün, 19x dunkelgrün Größe 60x42: 16x pink, 2x dunkelgrün; 42x30cm: 19x pink | H8: Verbrauchsmaterial | J8: B | K8: Konvolut | M8: neuwertig | O8: =F8-IF(N8="",0,N8) | P8: ja | S8: 50 | T8: Fix | U8: ok | V8: =O8*S8 | W8: nur Abholung | X8: F-555 | Y8: ja | Z8: verfügbar | AF8: =IF(N8="","",N8*AE8) | AM8: verschiedene Farben und Größen
B9: BA09-01 | C9: BA09 | D9: Personalraum | E9: Deko Metallruten mit Pompons | F9: 2 | G9: Metallruten mit roten Wollbommeln in Birkenstammfuß | H9: Deko | J9: C | K9: Stück | M9: gut | O9: =F9-IF(N9="",0,N9) | P9: ja | S9: 15 | T9: Fix | U9: ok | V9: =O9*S9 | W9: nur Abholung | X9: F-044 | Y9: ja | Z9: verfügbar | AF9: =IF(N9="","",N9*AE9) | AN9: Notiz aus der ersten Liste: 2 Stück im Bild
B10: BA09-02 | C10: BA09 | D10: Personalraum | E10: Elefantenfuß groß | F10: 1 | G10: Beaucarnea, große Zimmerpflanze im Topf und kleine Zimmerpflanze im Topf | H10: Pflanzen | J10: C | K10: Set | M10: gut | O10: =F10-IF(N10="",0,N10) | P10: ja | S10: 30 | T10: Fix | U10: ok | V10: =O10*S10 | W10: nur Abholung | X10: F-045 | Y10: ja | Z10: verfügbar | AF10: =IF(N10="","",N10*AE10) | AN10: Notiz aus der ersten Liste: 1 Pflanze im Bild
B11: BA09-03 | C11: BA09 | D11: Personalraum | E11: Werte-Rad | F11: 1 | G11: Drehbares Holzrad zur Visualisierung von Leitwerten, Eigenbau | H11: Kita-Ausstattung | J11: C | K11: Stück | M11: gut | O11: =F11-IF(N11="",0,N11) | P11: ja | S11: 40 | T11: Fix | U11: ok | V11: =O11*S11 | W11: nur Abholung | X11: F-046 | Y11: ja | Z11: verfügbar | AF11: =IF(N11="","",N11*AE11) | AN11: Notiz aus der ersten Liste: 1 Stück im Bild
B12: BA09-04 | C12: BA09 | D12: Personalraum | E12: USM Haller Tisch | F12: 1 | G12: USM Haller, weiße Tischplatte, verchromtes Rohrgestell mit Kugelverbindern, ca. 200 x 100 cm | H12: Möbel | J12: A | K12: Stück | M12: gut | O12: =F12-IF(N12="",0,N12) | P12: ja | S12: 750 | T12: VHB | U12: ok | V12: =O12*S12 | W12: nur Abholung | X12: F-047 | Y12: ja | Z12: verfügbar | AA12: USM Haller | AB12: Designklassiker | AF12: =IF(N12="","",N12*AE12) | AN12: Notiz aus der ersten Liste: 1 Tisch im Bild
B13: BA09-05 | C13: BA09 | D13: Personalraum | E13: Kartell Masters Stuhl | F13: 4 | G13: Kartell Masters, Design Philippe Starck, schwarz | H13: Möbel | J13: A | K13: Stück | M13: gebraucht | O13: =F13-IF(N13="",0,N13) | P13: ja | Q13: 670026 | R13: 690.02 | S13: 120 | T13: Fix | U13: ok | V13: =O13*S13 | W13: nur Abholung | X13: F-048 | Y13: ja | Z13: verfügbar | AA13: Kartell | AB13: Designklassiker | AF13: =IF(N13="","",N13*AE13) | AM13: insgesamt 4 Stück
B14: BA10-01 | C14: BA10 | D14: Ruheraum | E14: Glastisch rund mit Chromgestell | F14: 1 | G14: Runde Glasplatte teilsatiniert, Chromgestell inkl. 4 Stühle 105 cm Durchmesser | H14: Möbel | J14: B | K14: Stück | M14: gebraucht | O14: =F14-IF(N14="",0,N14) | P14: ja | S14: 150 | T14: Fix | U14: ok | V14: =O14*S14 | W14: nur Abholung | X14: F-057 | Y14: ja | Z14: verfügbar | AF14: =IF(N14="","",N14*AE14) | AN14: Notiz aus der ersten Liste: 1 Tisch im Bild
B15: BA10-02 | C15: BA10 | D15: Ruheraum | E15: Samtsofa bordeaux, 2-Sitzer | F15: 2 | G15: Samtbezug dunkelrot, gesteppte Rückenlehne, dunkle Holzbeine ca. 160cm breit | H15: Möbel | J15: B | K15: Stück | M15: gebraucht | O15: =F15-IF(N15="",0,N15) | P15: ja | Q15: 670017 | R15: 585.33 | S15: 300 | T15: VHB | U15: ok | V15: =O15*S15 | W15: nur Abholung | X15: F-058 | Y15: ja | Z15: verfügbar | AF15: =IF(N15="","",N15*AE15) | AN15: Notiz aus der ersten Liste: 1 Sofa im Bild
B16: BA10-03 | C16: BA10 | D16: Ruheraum | E16: Sessel mit Bezug, weiß lackiert | F16: 2 | G16: Relaxsessel Alcantara, Alu, hellgrauer Bezug, mit Nackenkissen; Sitzteil ausziehbar als Fußauflage; Lehne verstellbar | H16: Möbel | J16: C | K16: Stück | M16: gebraucht | O16: =F16-IF(N16="",0,N16) | P16: ja | S16: 200 | T16: VHB | U16: ok | V16: =O16*S16 | W16: nur Abholung | X16: F-591 | Y16: ja | Z16: verfügbar | AF16: =IF(N16="","",N16*AE16) | AN16: Notiz aus der ersten Liste: 1 Sessel im Bild
B17: BA10-04 | C17: BA10 | D17: Ruheraum | E17: Hocker grau mit Hairpin-Beinen | F17: 1 | G17: Hocker grau Runder Polsterhocker grau, mit Stauraum ohne Deko | H17: Möbel | J17: C | K17: Stück | M17: gebraucht | O17: =F17-IF(N17="",0,N17) | P17: ja | S17: 35 | T17: Fix | U17: ok | V17: =O17*S17 | W17: nur Abholung | X17: F-592 | Y17: ja | Z17: verfügbar | AF17: =IF(N17="","",N17*AE17)
B18: BA10-05 | C18: BA10 | D18: Ruheraum | E18: Ohrensessel grau mit Kufengestell | F18: 2 | G18: Polstersessel hellgrau, schwarzes Kufengestell aus Rundstahl ohne Kissen / Auflage | H18: Möbel | J18: B | K18: Stück | M18: gebraucht | N18: 2 | O18: =F18-IF(N18="",0,N18) | P18: ja | S18: 100 | T18: Fix | U18: ok | V18: =O18*S18 | W18: nur Abholung | X18: F-594 | Y18: ja | Z18: verkauft | AC18: Webkatalog | AE18: 100 | AF18: =IF(N18="","",N18*AE18) | AG18: 16.10.2026 | AH18: Christian Migowski, Boos | AI18: 4000135, 4000116 | AJ18: bezahlt | AL18: 21.10.2026 07:30, 26.10.2026 08:00 | AN18: Notiz aus der ersten Liste: 2 Sessel im Bild
B19: BA10-06 | C19: BA10 | D19: Ruheraum | E19: Hocker grau, passend | F19: 2 | G19: Polsterhocker hellgrau, schwarzes Kufengestell, passend zu den Sesseln 45x50cm | H19: Möbel | J19: C | K19: Stück | M19: gebraucht | N19: 2 | O19: =F19-IF(N19="",0,N19) | P19: ja | S19: 30 | T19: Fix | U19: ok | V19: =O19*S19 | W19: nur Abholung | X19: F-056 | Y19: ja | Z19: verkauft | AC19: Webkatalog | AE19: 30 | AF19: =IF(N19="","",N19*AE19) | AG19: 16.10.2026 | AH19: Christian Migowski, Boos | AI19: 4000135, 4000116 | AJ19: bezahlt | AL19: 21.10.2026 07:30, 26.10.2026 08:00 | AN19: Notiz aus der ersten Liste: 2 Hocker im Bild
B20: BA10-07 | C20: BA10 | D20: Ruheraum | E20: Beistelltisch rund grau | F20: 1 | G20: Runde Platte grau, schwarze Hairpin-Beine; 50cm Durchmesser | H20: Möbel | J20: C | K20: Stück | M20: gut | O20: =F20-IF(N20="",0,N20) | P20: ja | S20: 30 | T20: Fix | U20: ok | V20: =O20*S20 | W20: nur Abholung | X20: F-593 | Y20: ja | Z20: verfügbar | AF20: =IF(N20="","",N20*AE20) | AN20: Notiz aus der ersten Liste: 1 Tisch im Bild
B21: BA10-08 | C21: BA10 | D21: Ruheraum | E21: Pendelleuchte Drahtgeflecht | F21: 2 | G21: Geometrische Drahtleuchte schwarz, Ikosaederform | H21: Leuchten | J21: C | K21: Stück | M21: gut | O21: =F21-IF(N21="",0,N21) | P21: ja | S21: 55 | T21: Fix | U21: ok | V21: =O21*S21 | W21: nur Abholung | X21: F-061 | Y21: ja | Z21: verfügbar | AF21: =IF(N21="","",N21*AE21) | AN21: Notiz aus der ersten Liste: 1 Leuchte im Bild
B22: BA12-01 | C22: BA12 | D22: Personal-WC | E22: Ast-Mobile mit Papierwaben | F22: 1 | G22: Deko-Mobile: Birkenast mit Papierwaben, Sternen und Filzhäusern | H22: Deko | J22: C | K22: Stück | M22: gut | O22: =F22-IF(N22="",0,N22) | P22: ja | S22: 30 | T22: Fix | U22: ok | V22: =O22*S22 | W22: nur Abholung | X22: F-055 | Y22: ja | Z22: verfügbar | AF22: =IF(N22="","",N22*AE22) | AN22: Notiz aus der ersten Liste: 1 Mobile im Bild
B23: BE01-01 | C23: BE01 | D23: Flur | E23: Barockspiegel schwarz, oval | F23: 3 | G23: Verzierter Rahmen schwarz, oval, zwei Größen | H23: Deko | J23: C | K23: Stück | M23: gut | O23: =F23-IF(N23="",0,N23) | P23: ja | S23: 45 | T23: Fix | U23: ok | V23: =O23*S23 | W23: nur Abholung | X23: F-051 | Y23: ja | Z23: verfügbar | AF23: =IF(N23="","",N23*AE23) | AN23: Notiz aus der ersten Liste: 2 Stück im Bild
B24: BE01-02 | C24: BE01 | D24: Flur | E24: Bilderrahmen mit Kinderzeichnung | F24: 3 | G24: Gerahmte Kinderzeichnungen/Drucke, schwarz gerahmt | H24: Deko | J24: C | K24: Set | M24: gut | O24: =F24-IF(N24="",0,N24) | P24: ja | S24: 30 | T24: Fix | U24: ok | V24: =O24*S24 | W24: nur Abholung | X24: F-053 | Y24: ja | Z24: verfügbar | AF24: =IF(N24="","",N24*AE24) | AN24: Notiz aus der ersten Liste: 3 Rahmen im Bild
B25: BE01-03 | C25: BE01 | D25: Flur | E25: Wandregal-Würfel schwarz | F25: 2 | G25: Offene Regalwürfel zur Wandmontage, schwarz | H25: Möbel | J25: C | K25: Stück | M25: gut | O25: =F25-IF(N25="",0,N25) | P25: ja | S25: 40 | T25: Fix | U25: ok | V25: =O25*S25 | W25: nur Abholung | X25: F-054 | Y25: ja | Z25: verfügbar | AF25: =IF(N25="","",N25*AE25) | AM25: bestehend aus 2 Würfeln | AN25: Sie stehen inzwischen im Atelier (BA08) – die Nummer BE01-03 bleibt.
B26: BE06-01 | C26: BE06 | D26: Gruppenraum | E26: Wandgestell Holz mit Schnüren | F26: 1 | G26: Holzrahmen mit gespannten Schnüren und Wäscheklammern zum Aufhängen von Bildern | H26: Kita-Ausstattung | J26: C | K26: Stück | M26: gebraucht | O26: =F26-IF(N26="",0,N26) | P26: ja | S26: 45 | T26: Fix | U26: ok | V26: =O26*S26 | W26: nur Abholung | X26: F-042 | Y26: ja | Z26: verfügbar | AF26: =IF(N26="","",N26*AE26) | AN26: Notiz aus der ersten Liste: 1 Stück im Bild
B27: BE06-02 | C27: BE06 | D27: Gruppenraum | E27: Designsofa anthrazit | F27: 1 | G27: Geschwungene Form, Wollstoff anthrazit, dunkle Metallbeine, 3-Sitzer | H27: Möbel | J27: A | K27: Stück | M27: gut | N27: 1 | O27: =F27-IF(N27="",0,N27) | P27: ja | Q27: 670012 | R27: 1198 | S27: 650 | T27: VHB | U27: ok | V27: =O27*S27 | W27: nur Abholung | X27: F-043 | Y27: ja | Z27: verkauft | AC27: Webkatalog | AE27: 600 | AF27: =IF(N27="","",N27*AE27) | AG27: 19.10.2026 | AH27: Hagen Rebholz | AI27: 4000133 | AJ27: bezahlt | AL27: 21.10.2026 07:30 | AN27: Notiz aus der ersten Liste: 1 Sofa im Bild
B28: BE10-01 | C28: BE10 | D28: Büro und Besprechung | E28: LED-Ring-Pendelleuchte | F28: 1 | G28: Große Pendelleuchte: mehrere beleuchtete Ringe in unterschiedlichen Größen an dünnen Seilen, 2x 80cm Durchmesser, 2x ca. 60cm Durchmesser | H28: Leuchten | J28: A | K28: Set | M28: gut | N28: 1 | O28: =F28-IF(N28="",0,N28) | P28: ja | S28: 400 | T28: VHB | U28: ok | V28: =O28*S28 | W28: nur Abholung | X28: F-021 | Y28: ja | Z28: verkauft | AC28: Webkatalog | AE28: 400 | AF28: =IF(N28="","",N28*AE28) | AG28: 19.10.2026 | AH28: Hagen Rebholz | AI28: 4000133 | AJ28: bezahlt | AL28: 21.10.2026 07:30 | AM28: Set aus 4 Leuchten (2 × Ø 80 cm, 2 × Ø ca. 60 cm), nur zusammen. | AN28: 16.10.: alle 4 Leuchten als 1 Set für 400 € an Rebholz (#49, RG 4000133).
B29: BE10-02 | C29: BE10 | D29: Büro und Besprechung | E29: Pachira groß im Übertopf | F29: 1 | G29: Glückskastanie, große Pflanze, weißer Übertopf | H29: Pflanzen | J29: C | K29: Stück | M29: gut | O29: =F29-IF(N29="",0,N29) | P29: ja | S29: 80 | T29: Fix | U29: ok | V29: =O29*S29 | W29: nur Abholung | X29: F-025 | Y29: ja | Z29: verfügbar | AF29: =IF(N29="","",N29*AE29) | AN29: Notiz aus der ersten Liste: 1 Pflanze im Bild
B30: BE10-03 | C30: BE10 | D30: Büro und Besprechung | E30: Moderationswand fahrbar | F30: 1 | G30: Pinnwand/Stellwand grau, auf Rollen, beidseitig Höhe Wand: 150; Gesamthöhe: 185cm; Breite: 120cm | H30: Büro | J30: B | K30: Stück | M30: gut | O30: =F30-IF(N30="",0,N30) | P30: ja | S30: 50 | T30: Fix | U30: ok | V30: =O30*S30 | W30: nur Abholung | X30: F-026 | Y30: ja | Z30: reserviert | AC30: Webkatalog | AD30: Ricarda König | AF30: =IF(N30="","",N30*AE30) | AI30: 4000143 | AL30: 16.11.2026 09:00 | AN30: Notiz aus der ersten Liste: 1 Stück im Bild
B31: BE10-04 | C31: BE10 | D31: Büro und Besprechung | E31: Besprechungstisch weiß, Hersteller MDF Italia "Tense" groß 100x270cm | F31: 1 | G31: Konferenztisch Hersteller: MDF Italia "Tense", weiße Platte, für ca. 8-10 Personen | H31: Büro | J31: B | K31: Stück | M31: gut | O31: =F31-IF(N31="",0,N31) | P31: entfällt | S31: 2500 | T31: VHB | V31: =O31*S31 | W31: nur Abholung | X31: F-616 | Y31: ja | Z31: verfügbar | AA31: MDF Italia | AF31: =IF(N31="","",N31*AE31) | AN31: Neues Foto F-616 (Durchsicht 01.10.2026). Entfällt laut Durchsicht 05.10.2026.
B32: BU04-01 | C32: BU04 | D32: Gruppenraum | E32: Crassula im Topf | F32: 2 | G32: Geldbaum, Zimmerpflanze im weißen Topf | H32: Pflanzen | J32: C | K32: Stück | M32: gut | O32: =F32-IF(N32="",0,N32) | P32: ja | S32: 15 | T32: Fix | U32: ok | V32: =O32*S32 | W32: nur Abholung | X32: F-078 | Y32: ja | Z32: verfügbar | AF32: =IF(N32="","",N32*AE32) | AN32: Notiz aus der ersten Liste: 1 Pflanze im Bild
B33: BU04-02 | C33: BU04 | D33: Gruppenraum | E33: Pflanzkübel Raumteiler weiß Hochglanz | F33: 1 | G33: Rechteckiger Pflanzkübel als Raumteiler, weiß hochglanz, ca. 80 x 30 x 80 cm | H33: Pflanzen | J33: B | K33: Stück | M33: gut | O33: =F33-IF(N33="",0,N33) | P33: ja | S33: 150 | T33: Fix | U33: ok | V33: =O33*S33 | W33: nur Abholung | X33: F-079 | Y33: ja | Z33: verfügbar | AF33: =IF(N33="","",N33*AE33) | AM33: inkl. Bepflanzung | AN33: Der Kübel steht inzwischen im Schlafraum 5 (NU04) – die Nummer BU04-02 bleibt.
B34: BU04-03 | C34: BU04 | D34: Gruppenraum | E34: Hochflorteppich beige, rund | F34: 2 | G34: Runder Hochflorteppich in Beige, 100 % Polypropylen, Flor hoch. Etikett auf der Unterseite: IKEA, 195 cm Durchmesser, 9,85 kg. | H34: Textilien | I34: NU02-10 | J34: C | K34: Stück | L34: Ø 195 cm | M34: gebraucht | O34: =F34-IF(N34="",0,N34) | P34: ja | S34: 40 | T34: Fix | U34: ok | V34: =O34*S34 | W34: nur Abholung | X34: F-150 | Y34: ja | Z34: verfügbar | AA34: IKEA | AF34: =IF(N34="","",N34*AE34) | AN34: Zusammengefasste Position – Post-it-Nummer im zweiten Raum: NU02-10. Frueherer Mengenhinweis: 2 Teppiche insgesamt: einer im Gruppenraum (BU04-03) und einer im Gruppenraum 5 (dort mit NU02-10 beschriftet).
B35: BU04-04 | C35: BU04 | D35: Gruppenraum | E35: Regal weiß, 4 Fächer (IKEA Kallax) | F35: 4 | G35: IKEA Kallax 2x2, weiß, vier Fächer. | H35: Möbel | I35: NU02-06 | J35: B | K35: Stück | M35: gebraucht | O35: =F35-IF(N35="",0,N35) | P35: ja | S35: 45 | T35: Fix | U35: ok | V35: =O35*S35 | W35: nur Abholung | X35: F-080 | Y35: ja | Z35: verfügbar | AA35: IKEA | AF35: =IF(N35="","",N35*AE35) | AN35: Zusammengefasste Position – Post-it-Nummer im zweiten Raum: NU02-06. Frueherer Mengenhinweis: 4 Regale insgesamt: 2 im Gruppenraum (BU04-04) und 2 im Gruppenraum 5 (dort mit NU02-06 beschriftet).
B36: K-117 | C36: BU04 | D36: Gruppenraum | E36: Wanddeko Fadenbilder | F36: 5 | G36: Fadenbilder auf Holzreifen, ohne Spiegelelemente; rot und schwarz; unterschiedliche Durchmesser | H36: Deko | J36: C | K36: Set | M36: gut | O36: =F36-IF(N36="",0,N36) | P36: nein | S36: 10 | T36: Fix | V36: =O36*S36 | W36: nur Abholung | X36: F-081 | Y36: nein | Z36: entfällt | AF36: =IF(N36="","",N36*AE36) | AM36: 1 Set im Bild | AN36: Nicht mehr vorhanden – von der Nutzerin am 23.09.2026 bestaetigt. Frueher BU04-05 / K-117; die Nummer BU04-05 klebt jetzt auf den Hochstuehlen. | 12.10.2026: Nummer BU04-16 an das Steckspielzeug abgegeben (Post-it klebt dort), diese entfallene Position trägt wieder ihre alte Nummer K-117.
B37: BU09-01 | C37: BU09 | D37: Werkraum | E37: Wurzelholz-Schale groß | F37: 1 | G37: Dekoschale aus einem Wurzelstück, Teak, ca. 50 cm | H37: Deko | J37: B | K37: Stück | M37: gut | O37: =F37-IF(N37="",0,N37) | P37: ja | S37: 90 | T37: Fix | U37: ok | V37: =O37*S37 | W37: nur Abholung | X37: F-082 | Y37: ja | Z37: verfügbar | AF37: =IF(N37="","",N37*AE37) | AN37: Notiz aus der ersten Liste: 1 Stück im Bild
B38: BU09-02 | C38: BU09 | D38: Werkraum | E38: Konvolut Baumscheiben und Holzscheiben | F38: 1 | G38: Baumscheiben verschiedener Größen und Holzarten, Bastelmaterial ca. 44 grössere mit Durchmesser zwischen 15 und35cm; 35 Stück mit durchmeser ca. 10-15cm | H38: Verbrauchsmaterial | J38: C | K38: Konvolut | M38: gut | N38: 1 | O38: =F38-IF(N38="",0,N38) | P38: ja | S38: 40 | T38: Fix | U38: ok | V38: =O38*S38 | W38: nur Abholung | X38: F-085 | Y38: ja | Z38: verkauft | AC38: Webkatalog | AE38: 40 | AF38: =IF(N38="","",N38*AE38) | AG38: 19.10.2026 | AH38: Sandra Ziegler | AI38: 4000123 | AJ38: bezahlt | AL38: 20.10.2026 14:15 | AM38: Mehrere Kisten mit Baum- und Holzscheiben in verschiedenen Größen | AN38: Notiz aus der ersten Liste: mehrere Kisten im Bild
B39: BU09-03 | C39: BU09 | D39: Werkraum | E39: Kreidetafel in Hausform | F39: 3 | G39: Tafelfolie/Kreidetafel in Hausform, beschriftbar | H39: Kita-Ausstattung | J39: C | K39: Stück | M39: gut | O39: =F39-IF(N39="",0,N39) | P39: ja | S39: 10 | T39: Fix | U39: ok | V39: =O39*S39 | W39: nur Abholung | X39: F-089 | Y39: ja | Z39: verfügbar | AF39: =IF(N39="","",N39*AE39) | AN39: Notiz aus der ersten Liste: 1 Stück im Bild
B40: GA01-01 | C40: GA01 | D40: Garten | E40: Holz-Wellenliege, Doppelliege | F40: 1 | G40: Geschwungene Doppelliege aus Holzlatten, ca. 200 cm breit, | H40: Garten | J40: A | K40: Stück | M40: gut | O40: =F40-IF(N40="",0,N40) | P40: ja | S40: 850 | T40: VHB | U40: ok | V40: =O40*S40 | W40: nur Abholung | X40: F-111 | Y40: ja | Z40: verfügbar | AB40: Außenbereich | AF40: =IF(N40="","",N40*AE40) | AN40: Notiz aus der ersten Liste: 1 Liege im Bild
B41: K-002 | C41: NU02 | D41: Gruppenraum | E41: Kommode weiß, 9 Schubladen | F41: 1 | G41: IKEA Nordli, weiß, drei Module nebeneinander, insgesamt 9 Schubladen | H41: Möbel | J41: B | K41: Stück | M41: gut | O41: =F41-IF(N41="",0,N41) | P41: entfällt | S41: 120 | T41: Fix | V41: =O41*S41 | W41: nur Abholung | X41: F-002 | Y41: ja | Z41: verfügbar | AF41: =IF(N41="","",N41*AE41) | AM41: 1 Einheit aus 3 Modulen im Bild | AN41: Von der Nutzerin am 24.09.2026 geprueft: kommt nicht in den Katalog. Die Zeile bleibt nur zur Nachvollziehbarkeit der alten K-Nummer stehen.
B42: K-003 | C42: NU02 | D42: Gruppenraum | E42: Deko-Set Globus, Letterboard, Rahmen | F42: 1 | G42: Globus, Steckbuchstaben-Board, Bilderrahmen auf Staffelei | H42: Deko | J42: C | K42: Set | M42: gut | O42: =F42-IF(N42="",0,N42) | P42: entfällt | S42: 35 | T42: Fix | V42: =O42*S42 | W42: nur Abholung | X42: F-002 | Y42: ja | Z42: verfügbar | AF42: =IF(N42="","",N42*AE42) | AM42: 3 Teile im Bild | AN42: Von der Nutzerin am 24.09.2026 geprueft: kommt nicht in den Katalog. Die Zeile bleibt nur zur Nachvollziehbarkeit der alten K-Nummer stehen.
B43: K-005 | C43: NU02 | D43: Gruppenraum | E43: Mal- und Trockengestell fahrbar | F43: 1 | G43: Drahtgittergestell auf Rollen, zum Trocknen und Präsentieren von Bildern | H43: Kita-Ausstattung | J43: C | K43: Stück | M43: gut | O43: =F43-IF(N43="",0,N43) | P43: entfällt | S43: 60 | T43: Fix | V43: =O43*S43 | W43: nur Abholung | X43: F-003 | Y43: ja | Z43: verfügbar | AF43: =IF(N43="","",N43*AE43) | AM43: 1 Stück im Bild | AN43: Von der Nutzerin am 24.09.2026 geprueft: kommt nicht in den Katalog. Die Zeile bleibt nur zur Nachvollziehbarkeit der alten K-Nummer stehen.
B44: K-006 | C44: NU02 | D44: Gruppenraum | E44: Kindertafel Holz | F44: 1 | G44: Standtafel/Staffelei aus Holz mit Kreidetafel | H44: Kita-Ausstattung | J44: C | K44: Stück | M44: gebraucht | O44: =F44-IF(N44="",0,N44) | P44: entfällt | S44: 35 | T44: Fix | V44: =O44*S44 | W44: nur Abholung | X44: F-003 | Y44: ja | Z44: verfügbar | AF44: =IF(N44="","",N44*AE44) | AM44: 1 Stück im Bild | AN44: Von der Nutzerin am 24.09.2026 geprueft: kommt nicht in den Katalog. Die Zeile bleibt nur zur Nachvollziehbarkeit der alten K-Nummer stehen.
B45: K-010 | C45: NU04 | D45: Schlafraum | E45: Pinnwand gerahmt | F45: 1 | G45: Pinnwand mit Holzrahmen | H45: Büro | J45: C | K45: Stück | M45: gut | O45: =F45-IF(N45="",0,N45) | P45: entfällt | S45: 25 | T45: Fix | V45: =O45*S45 | W45: nur Abholung | X45: F-006 | Y45: ja | Z45: verfügbar | AF45: =IF(N45="","",N45*AE45) | AM45: 1 Stück im Bild | AN45: Von der Nutzerin am 24.09.2026 geprueft: kommt nicht in den Katalog. Die Zeile bleibt nur zur Nachvollziehbarkeit der alten K-Nummer stehen.
B46: K-013 | C46: NU04 | D46: Schlafraum | E46: Kuckucksuhr klein | F46: 1 | G46: Schwarzwälder Kuckucksuhr, kleine Ausführung, Holz | H46: Uhren | J46: A | K46: Stück | M46: gut | O46: =F46-IF(N46="",0,N46) | P46: entfällt | S46: 90 | T46: Fix | V46: =O46*S46 | W46: nur Abholung | X46: F-008 | Y46: ja | Z46: verfügbar | AF46: =IF(N46="","",N46*AE46) | AM46: 1 Stück im Bild | AN46: Von der Nutzerin am 24.09.2026 geprueft: kommt nicht in den Katalog. Die Zeile bleibt nur zur Nachvollziehbarkeit der alten K-Nummer stehen.
B47: K-016 | C47: NU04 | D47: Schlafraum | E47: Regal mit Aufbewahrungsboxen | F47: 3 | G47: IKEA Trofast, Holzrahmen mit Kunststoffboxen | H47: Kita-Ausstattung | J47: C | K47: Stück | M47: gebraucht | O47: =F47-IF(N47="",0,N47) | P47: entfällt | S47: 35 | T47: Fix | V47: =O47*S47 | W47: nur Abholung | X47: F-011 | Y47: ja | Z47: verfügbar | AF47: =IF(N47="","",N47*AE47) | AM47: 3 Regale im Bild erkennbar | AN47: Von der Nutzerin am 24.09.2026 geprueft: kommt nicht in den Katalog. Die Zeile bleibt nur zur Nachvollziehbarkeit der alten K-Nummer stehen.
B48: K-017 | C48: NU04 | D48: Schlafraum | E48: Kinderwerkbank Holz | F48: 1 | G48: Werkbank für Kinder mit Schraubstock und Zubehör | H48: Kita-Ausstattung | J48: C | K48: Stück | M48: gebraucht | O48: =F48-IF(N48="",0,N48) | P48: entfällt | S48: 60 | T48: Fix | V48: =O48*S48 | W48: nur Abholung | X48: F-011 | Y48: ja | Z48: verfügbar | AF48: =IF(N48="","",N48*AE48) | AM48: 1 Stück im Bild | AN48: Von der Nutzerin am 24.09.2026 geprueft: kommt nicht in den Katalog. Die Zeile bleibt nur zur Nachvollziehbarkeit der alten K-Nummer stehen.
B49: K-018 | C49: NE01 | D49: Flur | E49: Pompon-Kronleuchter rot | F49: 1 | G49: Metallring-Konstruktion mit roten Wollbommeln, Sonderanfertigung, Deckenleuchte | H49: Leuchten | J49: B | K49: Stück | M49: gut | O49: =F49-IF(N49="",0,N49) | P49: entfällt | S49: 150 | T49: Fix | V49: =O49*S49 | W49: nur Abholung | X49: F-012 | Y49: ja | Z49: verfügbar | AF49: =IF(N49="","",N49*AE49) | AM49: 1 Stück im Bild | AN49: Von der Nutzerin am 24.09.2026 geprueft: kommt nicht in den Katalog. Die Zeile bleibt nur zur Nachvollziehbarkeit der alten K-Nummer stehen.
B50: K-019 | C50: NE01 | D50: Flur | E50: Wandbild Schwarzwald-Trachten, großformatig | F50: 2 | G50: Fotodruck auf Leinwand/Alu-Dibond, Trachtenportrait, großformatig - Kaufware | H50: Kunst | J50: B | K50: Stück | M50: gut | O50: =F50-IF(N50="",0,N50) | P50: entfällt | S50: 120 | T50: Fix | V50: =O50*S50 | W50: nur Abholung | X50: F-013 | Y50: ja | Z50: verfügbar | AF50: =IF(N50="","",N50*AE50) | AM50: 2 Bilder im Bild | AN50: Von der Nutzerin am 24.09.2026 geprueft: kommt nicht in den Katalog. Die Zeile bleibt nur zur Nachvollziehbarkeit der alten K-Nummer stehen.
B51: K-021 | C51: NE01 | D51: Flur | E51: Wanddeko Holzleiter und Treibholz | F51: 1 | G51: Dekoleiter grau in Tannenform, dazu Treibholzelemente | H51: Deko | J51: C | K51: Set | M51: gut | O51: =F51-IF(N51="",0,N51) | P51: entfällt | S51: 30 | T51: Fix | V51: =O51*S51 | W51: nur Abholung | X51: F-015 | Y51: ja | Z51: verfügbar | AF51: =IF(N51="","",N51*AE51) | AM51: 1 Set im Bild | AN51: Von der Nutzerin am 24.09.2026 geprueft: kommt nicht in den Katalog. Die Zeile bleibt nur zur Nachvollziehbarkeit der alten K-Nummer stehen.
B52: K-022 | C52: NE01 | D52: Flur | E52: Zamioculcas groß im Übertopf | F52: 1 | G52: Glücksfeder, große Pflanze, schwarzer Übertopf | H52: Pflanzen | J52: C | K52: Stück | M52: gut | O52: =F52-IF(N52="",0,N52) | P52: entfällt | S52: 70 | T52: Fix | V52: =O52*S52 | W52: nur Abholung | X52: F-015 | Y52: ja | Z52: verfügbar | AF52: =IF(N52="","",N52*AE52) | AM52: 1 Pflanze im Bild | AN52: Von der Nutzerin am 24.09.2026 geprueft: kommt nicht in den Katalog. Die Zeile bleibt nur zur Nachvollziehbarkeit der alten K-Nummer stehen.
... B60: K-037 | C60: BE11 | D60: Büro | E60: Ringlicht LED auf Stativ | F60: 1 | G60: Fotolicht, Ringleuchte mit Stativ | H60: Technik | J60: C | K60: Stück | M60: gut | O60: =F60-IF(N60="",0,N60) | P60: entfällt | S60: 35 | T60: Fix | V60: =O60*S60 | W60: nur Abholung | X60: F-023 | Y60: ja | Z60: verfügbar | AF60: =IF(N60="","",N60*AE60) | AM60: 1 Stück im Bild | AN60: Von der Nutzerin am 24.09.2026 geprueft: kommt nicht in den Katalog. Die Zeile bleibt nur zur Nachvollziehbarkeit der alten K-Nummer stehen.
B61: BE10-09 | C61: BE10 | D61: Büro und Besprechung | E61: Konsolentisch schwarz mit Glasablagen | F61: 1 | G61: Schmaler Konsolentisch mit schwarzem Metallrahmen und zwei Ablagen aus Glas. | H61: Möbel | J61: C | K61: Stück | M61: gut | O61: =F61-IF(N61="",0,N61) | P61: ja | S61: 60 | T61: Fix | U61: ok | V61: =O61*S61 | W61: nur Abholung | X61: F-024 | Y61: ja | Z61: reserviert | AC61: Webkatalog | AD61: Simon fronius | AF61: =IF(N61="","",N61*AE61) | AL61: 01.12.2026 09:00 | AN61: Auf Foto F-024 steht er im Raum.
B62: K-039 | C62: BE10 | D62: Büro und Besprechung | E62: Kinderfahrzeug Kuh | F62: 1 | G62: Wheely-Bug-Typ, Rutschfahrzeug für Kinder, Plüsch mit Rollen | H62: Kita-Ausstattung | J62: C | K62: Stück | M62: gebraucht | O62: =F62-IF(N62="",0,N62) | P62: entfällt | S62: 35 | T62: Fix | V62: =O62*S62 | W62: nur Abholung | X62: F-024 | Y62: ja | Z62: verfügbar | AF62: =IF(N62="","",N62*AE62) | AM62: 1 Stück im Bild | AN62: Von der Nutzerin am 24.09.2026 geprueft: kommt nicht in den Katalog. Die Zeile bleibt nur zur Nachvollziehbarkeit der alten K-Nummer stehen.
B63: BE10-10 | C63: BE10 | D63: Büro und Besprechung | E63: Kommode Holz, antik | F63: 1 | G63: Alte Holzkommode beziehungsweise Sekretär in dunklem Holz. Die linke Tür schließt nicht mehr; der übrige Zustand ist gut. | H63: Möbel | J63: B | K63: Stück | M63: gebraucht | O63: =F63-IF(N63="",0,N63) | P63: entfällt | S63: 120 | T63: Fix | V63: =O63*S63 | W63: nur Abholung | X63: F-025 | Y63: ja | Z63: verfügbar | AF63: =IF(N63="","",N63*AE63) | AN63: Auf Foto F-025 steht sie im Raum.
B64: K-044 | C64: BE10 | D64: Büro und Besprechung | E64: Schalenstuhl weiß mit Holzbeinen | F64: 8 | G64: Kunststoff-Sitzschale weiß, Holzbeine mit Drahtstrebe | H64: Möbel | J64: B | K64: Stück | M64: gut | O64: =F64-IF(N64="",0,N64) | P64: entfällt | S64: 30 | T64: Fix | V64: =O64*S64 | W64: nur Abholung | X64: F-027 | Y64: ja | Z64: verfügbar | AF64: =IF(N64="","",N64*AE64) | AM64: ca. 8 Stück im Bild - bitte nachzählen | AN64: Ersetzt durch BE10-05. Die Zeile bleibt nur zur Nachvollziehbarkeit der alten K-Nummer stehen.
B65: BE10-11 | C65: BE10 | D65: Büro und Besprechung | E65: Bürodrehstuhl weiß | F65: 1 | G65: Bürodrehstuhl in Weiß auf fünf Rollen, Sitzhöhe verstellbar. | H65: Büro | J65: C | K65: Stück | M65: gebraucht | N65: 1 | O65: =F65-IF(N65="",0,N65) | P65: ja | S65: 60 | T65: Fix | U65: ok | V65: =O65*S65 | W65: nur Abholung | X65: F-617 | Y65: ja | Z65: verkauft | AC65: Webkatalog | AE65: 60 | AF65: =IF(N65="","",N65*AE65) | AG65: 13.10.2026 | AH65: Jonathan Kleinknecht | AI65: 4000117 | AJ65: bezahlt | AL65: abgeholt 13.10.2026 | AN65: Neues Foto F-617 (Durchsicht 01.10.2026).
B66: BE10-12 | C66: BE10 | D66: Büro und Besprechung | E66: IKEA Galant Aktenschrank weiß | F66: 2 | G66: IKEA Galant Büroschrank in Weiß: oben offene Fächer, unten Schiebetüren mit zwei Einlegeböden. 200 cm Höhe, 160 cm Breite | H66: Büro | J66: B | K66: Stück | M66: gut | O66: =F66-IF(N66="",0,N66) | P66: ja | S66: 90 | T66: Fix | U66: ok | V66: =O66*S66 | W66: nur Abholung | X66: F-636 | Y66: ja | Z66: reserviert | AA66: IKEA | AC66: Webkatalog | AD66: Nadine Zythke | AF66: =IF(N66="","",N66*AE66) | AL66: 17.11.2026 09:00 | AM66: Ohne Inhalt. | AN66: Neues Foto F-636 (07.10.2026) ersetzt F-618; Beschreibung an das Foto angepasst (Schiebetüren, 2 Einlegeböden innen). Beide Schränke baugleich. 07.10.2026: Mengenhinweis auf „Ohne Inhalt.“ gekürzt – Ablagefächer gehen mit (Nutzerin).
B67: K-048 | C67: NE01 | D67: Flur | E67: Wanddeko Fadenbild rot | F67: 1 | G67: Fadenbild/Mandala auf rundem Holzreif, rot | H67: Deko | J67: C | K67: Stück | M67: gut | O67: =F67-IF(N67="",0,N67) | P67: entfällt | S67: 30 | T67: Fix | V67: =O67*S67 | W67: nur Abholung | X67: F-029 | Y67: ja | Z67: verfügbar | AF67: =IF(N67="","",N67*AE67) | AM67: 1 Stück im Bild | AN67: Von der Nutzerin am 24.09.2026 geprueft: kommt nicht in den Katalog. Die Zeile bleibt nur zur Nachvollziehbarkeit der alten K-Nummer stehen.
B68: K-063 | C68: BE01 | D68: Flur | E68: Pompon-Kranz rot | F68: 1 | G68: Türkranz aus roten Wollbommeln, Eigenarbeit | H68: Deko | J68: C | K68: Stück | M68: gut | O68: =F68-IF(N68="",0,N68) | P68: entfällt | S68: 25 | T68: Fix | V68: =O68*S68 | W68: nur Abholung | X68: F-052 | Y68: ja | Z68: verfügbar | AF68: =IF(N68="","",N68*AE68) | AM68: 1 Stück im Bild | AN68: Von der Nutzerin am 24.09.2026 geprueft: kommt nicht in den Katalog. Die Zeile bleibt nur zur Nachvollziehbarkeit der alten K-Nummer stehen.
B69: K-067 | C69: NE01 | D69: Flur | E69: Laterne schwarz | F69: 1 | G69: Metall-Glas-Laterne, schwarz | H69: Deko | J69: C | K69: Stück | M69: gut | O69: =F69-IF(N69="",0,N69) | P69: entfällt | S69: 20 | T69: Fix | V69: =O69*S69 | W69: nur Abholung | X69: F-072 | Y69: ja | Z69: verfügbar | AF69: =IF(N69="","",N69*AE69) | AM69: 1 Stück im Bild | AN69: Von der Nutzerin am 24.09.2026 geprueft: kommt nicht in den Katalog. Die Zeile bleibt nur zur Nachvollziehbarkeit der alten K-Nummer stehen.
B70: K-069 | C70: NE01 | D70: Flur | E70: Deko-Ring schwarz auf Sockel | F70: 1 | G70: Skulpturaler Ring, schwarz, auf Standfuß | H70: Deko | J70: C | K70: Stück | M70: gut | O70: =F70-IF(N70="",0,N70) | P70: entfällt | S70: 30 | T70: Fix | V70: =O70*S70 | W70: nur Abholung | X70: F-073 | Y70: ja | Z70: verfügbar | AF70: =IF(N70="","",N70*AE70) | AM70: 1 Stück im Bild | AN70: Von der Nutzerin am 24.09.2026 geprueft: kommt nicht in den Katalog. Die Zeile bleibt nur zur Nachvollziehbarkeit der alten K-Nummer stehen.
B71: K-070 | C71: NU01 | D71: Eingang und Elternlounge | E71: Bodenvase Keramik beige, groß | F71: 1 | G71: Bodenvase, beige/creme, matt, groß | H71: Deko | J71: C | K71: Stück | M71: gut | O71: =F71-IF(N71="",0,N71) | P71: entfällt | S71: 90 | T71: Fix | V71: =O71*S71 | W71: nur Abholung | X71: F-090 | Y71: ja | Z71: verfügbar | AF71: =IF(N71="","",N71*AE71) | AM71: 1 Stück im Bild (ohne Treibholz) | AN71: Von der Nutzerin am 24.09.2026 geprueft: kommt nicht in den Katalog. Die Zeile bleibt nur zur Nachvollziehbarkeit der alten K-Nummer stehen.
B72: K-071 | C72: NU01 | D72: Eingang und Elternlounge | E72: Bodenvase Keramik beige, klein | F72: 1 | G72: Bodenvase, beige/creme, matt, kleiner | H72: Deko | J72: C | K72: Stück | M72: gut | O72: =F72-IF(N72="",0,N72) | P72: entfällt | S72: 60 | T72: Fix | V72: =O72*S72 | W72: nur Abholung | X72: F-090 | Y72: ja | Z72: verfügbar | AF72: =IF(N72="","",N72*AE72) | AM72: 1 Stück im Bild | AN72: Von der Nutzerin am 24.09.2026 geprueft: kommt nicht in den Katalog. Die Zeile bleibt nur zur Nachvollziehbarkeit der alten K-Nummer stehen.
B73: K-073 | C73: NU01 | D73: Eingang und Elternlounge | E73: Konsolentisch schwarz, schmal | F73: 1 | G73: Schmaler Metall-Konsolentisch, schwarz | H73: Möbel | J73: C | K73: Stück | M73: gut | O73: =F73-IF(N73="",0,N73) | P73: entfällt | S73: 70 | T73: Fix | V73: =O73*S73 | W73: nur Abholung | X73: F-092 | Y73: ja | Z73: verfügbar | AF73: =IF(N73="","",N73*AE73) | AM73: 1 Stück im Bild | AN73: Von der Nutzerin am 24.09.2026 geprueft: kommt nicht in den Katalog. Die Zeile bleibt nur zur Nachvollziehbarkeit der alten K-Nummer stehen.
B74: K-074 | C74: NU01 | D74: Eingang und Elternlounge | E74: Gemälde abstrakt schwarz-weiß | F74: 1 | G74: Acryl auf Leinwand, Querformat - Eigenarbeit einer Privatperson | H74: Kunst | J74: B | K74: Stück | M74: gut | O74: =F74-IF(N74="",0,N74) | P74: entfällt | S74: 150 | T74: Fix | V74: =O74*S74 | W74: nur Abholung | X74: F-092 | Y74: ja | Z74: verfügbar | AF74: =IF(N74="","",N74*AE74) | AM74: 1 Bild im Bild | AN74: Von der Nutzerin am 24.09.2026 geprueft: kommt nicht in den Katalog. Die Zeile bleibt nur zur Nachvollziehbarkeit der alten K-Nummer stehen.
B75: K-076 | C75: NU01 | D75: Eingang und Elternlounge | E75: Tretmülleimer 30 l | F75: 1 | G75: Brabantia, schwarz, 30 Liter | H75: Sonstiges | J75: C | K75: Stück | M75: gut | O75: =F75-IF(N75="",0,N75) | P75: entfällt | S75: 60 | T75: Fix | V75: =O75*S75 | W75: nur Abholung | X75: F-075 | Y75: ja | Z75: verfügbar | AF75: =IF(N75="","",N75*AE75) | AM75: 1 Stück im Bild | AN75: Von der Nutzerin am 24.09.2026 geprueft: kommt nicht in den Katalog. Die Zeile bleibt nur zur Nachvollziehbarkeit der alten K-Nummer stehen.
B76: K-081 | C76: BA09 | D76: Personalraum | E76: Clivie im Topf | F76: 1 | G76: Klivie, Zimmerpflanze | H76: Pflanzen | J76: C | K76: Stück | M76: gut | O76: =F76-IF(N76="",0,N76) | P76: entfällt | S76: 30 | T76: Fix | V76: =O76*S76 | W76: nur Abholung | X76: F-045 | Y76: ja | Z76: verfügbar | AF76: =IF(N76="","",N76*AE76) | AM76: 1 Pflanze im Bild | AN76: Von der Nutzerin am 24.09.2026 geprueft: kommt nicht in den Katalog. Die Zeile bleibt nur zur Nachvollziehbarkeit der alten K-Nummer stehen.
B77: K-088 | C77: BA10 | D77: Ruheraum | E77: Bogenlampe Chrom | F77: 1 | G77: Bogenleuchte, Chromgestell, weißer Kunststoffschirm | H77: Leuchten | J77: B | K77: Stück | M77: gut | O77: =F77-IF(N77="",0,N77) | P77: entfällt | S77: 130 | T77: Fix | V77: =O77*S77 | W77: nur Abholung | X77: F-059 | Y77: ja | Z77: verfügbar | AF77: =IF(N77="","",N77*AE77) | AM77: 1 Leuchte im Bild | AN77: Von der Nutzerin am 24.09.2026 geprueft: kommt nicht in den Katalog. Die Zeile bleibt nur zur Nachvollziehbarkeit der alten K-Nummer stehen.
B78: K-095 | C78: BA10 | D78: Ruheraum | E78: Käfigleuchte mit Holzsockel | F78: 1 | G78: Kleine Tischleuchte, Drahtkäfig auf Holzfuß | H78: Leuchten | J78: C | K78: Stück | M78: gut | O78: =F78-IF(N78="",0,N78) | P78: entfällt | S78: 30 | T78: Fix | V78: =O78*S78 | W78: nur Abholung | X78: F-061 | Y78: ja | Z78: verfügbar | AF78: =IF(N78="","",N78*AE78) | AM78: 1 Stück im Bild | AN78: Von der Nutzerin am 24.09.2026 geprueft: kommt nicht in den Katalog. Die Zeile bleibt nur zur Nachvollziehbarkeit der alten K-Nummer stehen.
... B95: K-141 | C95: TE02 | D95: Dachterrasse | E95: Bistro-Set schwarz Metall | F95: 1 | G95: Gartentisch mit 2 Stühlen, schwarzes Metall, klappbar | H95: Garten | J95: C | K95: Set | M95: gebraucht | O95: =F95-IF(N95="",0,N95) | P95: entfällt | S95: 90 | T95: Fix | V95: =O95*S95 | W95: nur Abholung | X95: F-107 | Y95: ja | Z95: verfügbar | AF95: =IF(N95="","",N95*AE95) | AM95: 1 Tisch mit 2 Stühlen im Bild | AN95: Von der Nutzerin am 24.09.2026 geprueft: kommt nicht in den Katalog. Die Zeile bleibt nur zur Nachvollziehbarkeit der alten K-Nummer stehen.
B96: NE01-01 | C96: NE01 | D96: Flur | E96: Deko-Hirschkopf weiß | F96: 1 | G96: Kunstharz, weiß, mit schwarzem Geweih, auf Holzschild, Wandmontage | H96: Deko | J96: C | K96: Stück | M96: gut | N96: 1 | O96: =F96-IF(N96="",0,N96) | P96: ja | S96: 45 | T96: Fix | U96: ok | V96: =O96*S96 | W96: nur Abholung | X96: F-001 | Y96: ja | Z96: verkauft | AB96: Schwarzwald | AC96: Webkatalog | AE96: 45 | AF96: =IF(N96="","",N96*AE96) | AG96: 15.10.2026 | AH96: Tanja Fischer | AI96: 4000129 | AJ96: bezahlt | AL96: abgeholt 15.10.2026 | AN96: Notiz aus der ersten Liste: 1 Stück im Bild
B97: NE01-02 | C97: NE01 | D97: Flur | E97: Trachtenfotografie gerahmt, schwarz | F97: 30 | G97: Trachtenfotografien von Wehrle, Fotodruck im schwarzen Rahmen mit Passepartout, ca. 30 x 40 cm - Kaufware | H97: Kunst | J97: B | K97: Stück | M97: gut | N97: 1 | O97: =F97-IF(N97="",0,N97) | P97: ja | S97: 10 | T97: Fix | U97: ok | V97: =O97*S97 | W97: nur Abholung | X97: F-014 | Y97: ja | Z97: teilverkauft | AB97: Schwarzwald | AC97: Webkatalog | AE97: 10 | AF97: =IF(N97="","",N97*AE97) | AG97: 15.10.2026 | AH97: Tanja Fischer | AI97: 4000129 | AJ97: bezahlt | AL97: abgeholt 15.10.2026 | AM97: 30 gerahmte Fotografien mit verschiedenen Motiven; das Foto zeigt eine Auswahl. | AN97: Durchsicht 01.10.2026: Menge auf 30 erhöht, Preis von 45 auf 35 € gesenkt. NE01-03 und NU01-08 sind dafür herausgenommen.
B98: NE01-03 | C98: NE01 | D98: Flur | E98: Trachtenportrait gerahmt, klein | F98: 3 | G98: Fotodruck gerahmt, kleinformatig - Kaufware | H98: Kunst | J98: C | K98: Stück | M98: gut | O98: =F98-IF(N98="",0,N98) | P98: entfällt | S98: 35 | T98: Fix | V98: =O98*S98 | W98: nur Abholung | X98: F-029 | Y98: nein | Z98: verfügbar | AB98: Schwarzwald | AF98: =IF(N98="","",N98*AE98) | AN98: Durchsicht 01.10.2026: aus dem Katalog genommen, die gerahmten Fotografien laufen über NE01-02.
B99: NE01-04 | C99: NE01 | D99: Flur | E99: Gemälde Bollenhut abstrakt, schwarz-weiß | F99: 1 | G99: Acryl auf Leinwand, ca. 90 x 90 cm - Eigenarbeit einer Privatperson | H99: Kunst | J99: B | K99: Stück | M99: gut | O99: =F99-IF(N99="",0,N99) | P99: ja | S99: 150 | T99: Fix | U99: ok | V99: =O99*S99 | W99: nur Abholung | X99: F-030 | Y99: ja | Z99: verfügbar | AB99: Schwarzwald | AF99: =IF(N99="","",N99*AE99) | AN99: Notiz aus der ersten Liste: 1 Bild im Bild
B100: NE01-05 | C100: NE01 | D100: Flur | E100: Sansevieria groß im Übertopf | F100: 1 | G100: Bogenhanf, große Pflanze, weißer Übertopf | H100: Pflanzen | J100: C | K100: Stück | M100: gut | N100: 1 | O100: =F100-IF(N100="",0,N100) | P100: ja | S100: 60 | T100: Fix | U100: ok | V100: =O100*S100 | W100: nur Abholung | X100: F-031 | Y100: ja | Z100: verkauft | AC100: Webkatalog | AE100: 60 | AF100: =IF(N100="","",N100*AE100) | AG100: 13.10.2026 | AH100: Aljona Dura | AI100: 4000118 | AJ100: bezahlt | AL100: abgeholt 13.10.2026 | AN100: Notiz aus der ersten Liste: 1 Pflanze im Bild
B101: NE01-06 | C101: NE01 | D101: Flur | E101: Gemälde Bollenhut rot-weiß | F101: 1 | G101: Acryl auf Leinwand, ca. 50 x 60 cm - Eigenarbeit einer Privatperson | H101: Kunst | J101: B | K101: Stück | M101: gut | O101: =F101-IF(N101="",0,N101) | P101: ja | S101: 140 | T101: Fix | U101: ok | V101: =O101*S101 | W101: nur Abholung | X101: F-032 | Y101: ja | Z101: verfügbar | AB101: Schwarzwald | AF101: =IF(N101="","",N101*AE101) | AN101: Notiz aus der ersten Liste: 1 Bild im Bild
B102: NE01-07 | C102: NE01 | D102: Flur | E102: Holz-Schriftzug Heimat | F102: 1 | G102: Dekoschriftzug aus Holz | H102: Deko | J102: C | K102: Stück | M102: gut | O102: =F102-IF(N102="",0,N102) | P102: ja | S102: 25 | T102: Fix | U102: ok | V102: =O102*S102 | W102: nur Abholung | X102: F-032 | Y102: ja | Z102: verfügbar | AB102: Schwarzwald | AF102: =IF(N102="","",N102*AE102) | AN102: Notiz aus der ersten Liste: 1 Stück im Bild
B103: NE01-08 | C103: NE01 | D103: Flur | E103: Zamioculcas im Übertopf | F103: 1 | G103: Glücksfeder, weißer Übertopf | H103: Pflanzen | J103: C | K103: Stück | M103: gut | O103: =F103-IF(N103="",0,N103) | P103: ja | S103: 40 | T103: Fix | U103: ok | V103: =O103*S103 | W103: nur Abholung | X103: F-033 | Y103: ja | Z103: verfügbar | AF103: =IF(N103="","",N103*AE103) | AN103: Notiz aus der ersten Liste: 1 Pflanze im Bild
B104: NE01-09 | C104: NE01 | D104: Flur | E104: Wanddeko Fadenbild schwarz | F104: 2 | G104: Schwarzes Fadenbild auf rundem Holzreif, zwei Größen | H104: Deko | J104: C | K104: Stück | M104: gut | O104: =F104-IF(N104="",0,N104) | P104: nein | S104: 35 | T104: Fix | V104: =O104*S104 | W104: nur Abholung | X104: F-034 | Y104: nein | Z104: entfällt | AF104: =IF(N104="","",N104*AE104) | AM104: 2 Stück (klein und groß) | AN104: Nicht mehr vorhanden – von der Nutzerin am 24.09.2026 bestaetigt.
B105: NE01-10 | C105: NE01 | D105: Flur | E105: Deckenleuchte Pusteblume | F105: 3 | G105: IKEA Maskros, weiß, zwei Größen | H105: Leuchten | J105: C | K105: Stück | M105: gut | O105: =F105-IF(N105="",0,N105) | P105: ja | S105: 50 | T105: Fix | U105: ok | V105: =O105*S105 | W105: nur Abholung | X105: F-036 | Y105: ja | Z105: verfügbar | AF105: =IF(N105="","",N105*AE105)
B106: NE01-11 | C106: NE01 | D106: Flur | E106: Gemälde Bollenhut-Mädchen | F106: 1 | G106: Acryl auf Leinwand, ca. 50 x 70 cm - Eigenarbeit einer Privatperson | H106: Kunst | J106: B | K106: Stück | M106: gut | O106: =F106-IF(N106="",0,N106) | P106: ja | S106: 360 | T106: VHB | U106: ok | V106: =O106*S106 | W106: nur Abholung | X106: F-037 | Y106: ja | Z106: verfügbar | AB106: Schwarzwald | AF106: =IF(N106="","",N106*AE106) | AN106: Notiz aus der ersten Liste: 1 Bild im Bild
B107: NE01-12 | C107: NE01 | D107: Flur | E107: Gemälde Fuchs mit Bollenhut | F107: 1 | G107: Acryl auf Leinwand, ca. 80 x 100 cm - Eigenarbeit einer Privatperson | H107: Kunst | J107: B | K107: Stück | M107: gut | O107: =F107-IF(N107="",0,N107) | P107: ja | S107: 180 | T107: Fix | U107: ok | V107: =O107*S107 | W107: nur Abholung | X107: F-038 | Y107: ja | Z107: verfügbar | AB107: Schwarzwald | AF107: =IF(N107="","",N107*AE107) | AN107: Notiz aus der ersten Liste: 1 Bild im Bild
B108: NE01-13 | C108: NE01 | D108: Flur | E108: Gemälde Panorama, 3 Figuren | F108: 1 | G108: Acryl auf Leinwand, Querformat ca. 90 x 30 cm - Eigenarbeit einer Privatperson | H108: Kunst | J108: B | K108: Stück | M108: gut | O108: =F108-IF(N108="",0,N108) | P108: ja | S108: 100 | T108: Fix | U108: ok | V108: =O108*S108 | W108: nur Abholung | X108: F-040 | Y108: ja | Z108: verfügbar | AB108: Schwarzwald | AF108: =IF(N108="","",N108*AE108) | AN108: Notiz aus der ersten Liste: 1 Bild im Bild
B109: NE01-14 | C109: NE01 | D109: Flur | E109: Gemälde Panorama, 5 Figuren | F109: 1 | G109: Acryl auf Leinwand, Querformat - Eigenarbeit einer Privatperson 90x30 | H109: Kunst | J109: B | K109: Stück | M109: gut | O109: =F109-IF(N109="",0,N109) | P109: ja | S109: 100 | T109: Fix | U109: ok | V109: =O109*S109 | W109: nur Abholung | X109: F-041 | Y109: ja | Z109: verfügbar | AB109: Schwarzwald | AF109: =IF(N109="","",N109*AE109) | AN109: Notiz aus der ersten Liste: 1 Bild im Bild
B110: NE01-15 | C110: NE01 | D110: Flur | E110: Deko-Tannenbaum schwarz | F110: 3 | G110: Metall-Tannenbaum auf Holzsockel, schwarz, verschiedene Größen | H110: Deko | J110: C | K110: Stück | M110: gut | O110: =F110-IF(N110="",0,N110) | P110: entfällt | S110: 25 | T110: Fix | V110: =O110*S110 | W110: nur Abholung | X110: F-072 | Y110: ja | Z110: verfügbar | AF110: =IF(N110="","",N110*AE110) | AM110: 3 Stück im Bild | AN110: Auf dem Erfassungsblatt NE01 durchgestrichen - die Stuecke stehen jetzt im Flur 1 und werden dort als BA01-03 gefuehrt.
B111: NE01-16 | C111: NE01 | D111: Flur | E111: Pflanze mit Topf | F111: 1 | G111: Pflanze mit Topf | H111: Pflanzen | J111: C | K111: Stück | M111: gut | O111: =F111-IF(N111="",0,N111) | P111: ja | S111: 20 | T111: Fix | U111: ok | V111: =O111*S111 | W111: nur Abholung | X111: F-073 | Y111: ja | Z111: verfügbar | AF111: =IF(N111="","",N111*AE111) | AN111: Notiz aus der ersten Liste: 2 Stück im Bild
B112: NE05-01 | C112: NE05 | D112: Speisesaal | E112: Massivholztisch mit Baumkante, Essbereich 160x85 | F112: 10 | G112: XXXLutz Massivholzplatte mit Baumkante, schwarzes Metallgestell mit Messingfüßen 160x80 | H112: Möbel | J112: A | K112: Stück | M112: gebraucht | N112: 1 | O112: =F112-IF(N112="",0,N112) | P112: ja | S112: 250 | T112: VHB | U112: ok | V112: =O112*S112 | W112: nur Abholung | X112: F-007 | Y112: ja | Z112: teilverkauft | AC112: Webkatalog | AE112: 250 | AF112: =IF(N112="","",N112*AE112) | AG112: 13.10.2026 | AH112: Boos | AI112: 4000116 | AJ112: bezahlt | AL112: 01.12.2026 09:00, 26.10.2026 08:00 | AM112: 10 gleiche Tische: 8 im Speisesaal, 2 im Gruppenraum. | AN112: Durchsicht 01.10.2026: NU04-03 (2 Stück, gleicher Tisch) zusammengelegt; Foto von NU04-03 übernommen. Das Post-it dort trägt weiter NU04-03.
B113: NE05-02 | C113: NE05 | D113: Speisesaal | E113: Sitzbank Massivholz | F113: 9 | G113: XXXLutz Passend zu den Baumkantentischen, Massivholz mit Metallgestell 160x40x52cm | H113: Möbel | J113: B | K113: Stück | M113: gebraucht | N113: 4 | O113: =F113-IF(N113="",0,N113) | P113: ja | S113: 50 | T113: Fix | U113: ok | V113: =O113*S113 | W113: nur Abholung | X113: F-016 | Y113: ja | Z113: teilverkauft | AC113: Webkatalog | AE113: 50 | AF113: =IF(N113="","",N113*AE113) | AG113: 15.10.2026 | AH113: Boos, Sonja Müller | AI113: 4000119, 4000116, 4000113 | AJ113: bezahlt | AL113: 26.10.2026 09:30, 01.12.2026 09:00, 26.10.2026 08:00, abgeholt 19.10.2026
B114: NE05-03 | C114: NE05 | D114: Speisesaal | E114: Kuckucksuhr groß, geschnitzt | F114: 1 | G114: Schwarzwälder Kuckucksuhr, aufwendig geschnitzt mit Hirschkopf, Eulen und Jagdhorn | H114: Uhren | J114: A | K114: Stück | M114: gut | O114: =F114-IF(N114="",0,N114) | P114: ja | S114: 550 | T114: VHB | U114: ok | V114: =O114*S114 | W114: nur Abholung | X114: F-017 | Y114: nein | Z114: verfügbar | AB114: Schwarzwald | AF114: =IF(N114="","",N114*AE114) | AN114: Notiz aus der ersten Liste: 1 Stück im Bild | 13.10.2026: auf Wunsch der Nutzerin aus dem Katalog genommen.
B115: NU01-01 | C115: NU01 | D115: Eingang und Elternlounge | E115: Vitra Alcove Sofa, rot | F115: 2 | G115: Vitra Alcove, Design Ronan & Erwan Bouroullec, rot, hohe Rückenwände, Chrombeine | H115: Möbel | J115: A | K115: Stück | M115: gebraucht | O115: =F115-IF(N115="",0,N115) | P115: ja | Q115: 630005 | R115: 1750 | S115: 1200 | T115: VHB | U115: ok | V115: =O115*S115 | W115: nur Abholung | X115: F-019 | Y115: ja | Z115: verfügbar | AA115: Vitra | AB115: Designklassiker | AF115: =IF(N115="","",N115*AE115) | AN115: Notiz aus der ersten Liste: 2 Elemente im Bild - bitte prüfen ob 3
B116: NU01-02 | C116: NU01 | D116: Eingang und Elternlounge | E116: Kuckucksuhr, Wandgruppe | F116: 5 | G116: Schwarzwälder Kuckucksuhren verschiedener Größe und Ausführung | H116: Uhren | J116: A | K116: Stück | M116: gut | N116: 1 | O116: =F116-IF(N116="",0,N116) | P116: ja | S116: 75 | T116: Fix | U116: ok | V116: =O116*S116 | W116: nur Abholung | X116: F-746 | Y116: ja | Z116: teilverkauft | AB116: Schwarzwald | AC116: Webkatalog | AE116: 75 | AF116: =IF(N116="","",N116*AE116) | AG116: 13.10.2026 | AH116: Aljona Dura | AI116: 4000118, 4000122 | AJ116: bezahlt | AL116: abgeholt 13.10.2026, 03.11.2026 08:30 | AM116: Verschiedene Ausführungen, Preis je Uhr. | AN116: 5 Uhren, Anzahl bestätigt am 06.10.2026. | 14.10.2026: neues Foto F-746 (ersetzt F-109). Menge bleibt 5 – eine verkauft und eine reserviert über den Katalog, WordPress zieht sie selbst ab.
B117: NU01-03 | C117: NU01 | D117: Eingang und Elternlounge | E117: Dekoration in der Vitrine | F117: 1 | G117: Dekoration in der Vitrine | H117: Deko | J117: B | K117: Stück | M117: gut | O117: =F117-IF(N117="",0,N117) | P117: entfällt | S117: 50 | T117: Fix | V117: =O117*S117 | W117: nur Abholung | X117: F-110 | Y117: ja | Z117: verfügbar | AF117: =IF(N117="","",N117*AE117) | AN117: Notiz aus der ersten Liste: 1 Stück im Bild (Inhalt nicht enthalten)
B118: NU01-04 | C118: NU01 | D118: Eingang und Elternlounge | E118: Gemälde Heimweh | F118: 1 | G118: Acryl auf Leinwand, großformatig ca. 100 x 140 cm - Eigenarbeit einer Privatperson | H118: Kunst | I118: BE01-08 | J118: B | K118: Stück | M118: gut | O118: =F118-IF(N118="",0,N118) | P118: ja | S118: 350 | T118: VHB | U118: ok | V118: =O118*S118 | W118: nur Abholung | X118: F-049 | Y118: ja | Z118: verfügbar | AB118: Schwarzwald | AF118: =IF(N118="","",N118*AE118) | AN118: Dasselbe Bild wurde zweimal beschriftet: NU01-04 und BE01-08. Menge bleibt 1. Frueherer Mengenhinweis: 1 Bild. Es trägt zusätzlich den Post-it BE01-08 aus dem Flur 1 des Bestandsgebäudes – es ist nur ein Bild, nicht zwei. Eine Nahaufnahme steht auf Foto F-493.
B119: NU01-05 | C119: NU01 | D119: Eingang und Elternlounge | E119: Deko-Hirschkopf geometrisch | F119: 2 | G119: Hirschkopf in geometrischer Form, Beton-/Holzoptik | H119: Deko | J119: C | K119: Stück | M119: gut | O119: =F119-IF(N119="",0,N119) | P119: ja | S119: 40 | T119: Fix | U119: ok | V119: =O119*S119 | W119: nur Abholung | X119: F-050 | Y119: ja | Z119: verfügbar | AB119: Schwarzwald | AF119: =IF(N119="","",N119*AE119) | AN119: Notiz aus der ersten Liste: 1 Stück im Bild
B120: NU01-06 | C120: NU01 | D120: Eingang und Elternlounge | E120: Gemälde Marilyn mit Bollenhut | F120: 1 | G120: Acryl auf Leinwand, großformatig ca. 90 x 90 cm - Eigenarbeit einer Privatperson | H120: Kunst | J120: B | K120: Stück | M120: gut | O120: =F120-IF(N120="",0,N120) | P120: ja | S120: 350 | T120: VHB | U120: ok | V120: =O120*S120 | W120: nur Abholung | X120: F-091 | Y120: ja | Z120: verfügbar | AB120: Schwarzwald | AF120: =IF(N120="","",N120*AE120) | AN120: Notiz aus der ersten Liste: 1 Bild im Bild
B121: NU01-07 | C121: NU01 | D121: Eingang und Elternlounge | E121: Trachtenportrait gerahmt, klein | F121: 1 | G121: Trachtenportrait gerahmt, klein | H121: Deko | J121: C | K121: Set | M121: gut | O121: =F121-IF(N121="",0,N121) | P121: entfällt | S121: 45 | T121: Fix | V121: =O121*S121 | W121: nur Abholung | X121: F-075 | Y121: ja | Z121: verfügbar | AB121: Schwarzwald | AF121: =IF(N121="","",N121*AE121) | AN121: Notiz aus der ersten Liste: 1 Stück im Bild
B122: NU01-08 | C122: NU01 | D122: Eingang und Elternlounge | E122: Trachtenfotografie gerahmt, weiß | F122: 5 | G122: Fotodruck im weißen Rahmen, ca. 20 x 25 cm - Kaufware | H122: Kunst | J122: C | K122: Stück | M122: gut | O122: =F122-IF(N122="",0,N122) | P122: entfällt | S122: 35 | T122: Fix | V122: =O122*S122 | W122: nur Abholung | X122: F-074 | Y122: ja | Z122: verfügbar | AB122: Schwarzwald | AF122: =IF(N122="","",N122*AE122) | AN122: Notiz aus der ersten Liste: 5 Rahmen im Bild
B123: NU01-09 | C123: NU01 | D123: Eingang und Elternlounge | E123: Trachtenfotografie gerahmt, schwarz | F123: 4 | G123: Fotodruck im schwarzen Rahmen mit Passepartout - Kaufware | H123: Kunst | J123: C | K123: Stück | M123: gut | O123: =F123-IF(N123="",0,N123) | P123: entfällt | S123: 35 | T123: Fix | V123: =O123*S123 | W123: nur Abholung | X123: F-075 | Y123: ja | Z123: verfügbar | AB123: Schwarzwald | AF123: =IF(N123="","",N123*AE123) | AN123: Notiz aus der ersten Liste: 4 Rahmen im Bild, ggf. mehr
...

Sheet Verkaufsübersicht
A1: Verkaufsübersicht – rechnet automatisch aus dem Artikelstamm
A2: Hier wird nichts eingetragen. Wer im Artikelstamm einen Verkauf erfasst, sieht ihn sofort hier.
A4: Bestand
A5: Artikelpositionen gesamt | B5: =COUNTA(Artikelstamm!$B$3:$B$729)
A6: davon verfügbar | B6: =COUNTIF(Artikelstamm!$Z$3:$Z$729,"verfügbar")
A7: davon reserviert | B7: =COUNTIF(Artikelstamm!$Z$3:$Z$729,"reserviert")
A8: davon teilverkauft | B8: =COUNTIF(Artikelstamm!$Z$3:$Z$729,"teilverkauft")
A9: davon verkauft | B9: =COUNTIF(Artikelstamm!$Z$3:$Z$729,"verkauft")
A10: Einheiten noch im Bestand | B10: =SUM(Artikelstamm!$O$3:$O$729)
A11: Restbestand zu Wunschpreisen | B11: =SUM(Artikelstamm!$V$3:$V$729)
A12: Erlöse
A13: Verkaufte Einheiten | B13: =SUM(Artikelstamm!$N$3:$N$729)
A14: Umsatz | B14: =SUMPRODUCT(Artikelstamm!$N$3:$N$729,Artikelstamm!$AE$3:$AE$729)
A15: Umsatzsteuer: keine (steuerfrei, § 4 Nr. 28 UStG) | B15: =B14*0.0
A16: Umsatz gesamt | B16: =B14+B15
A17: davon bereits bezahlt | B17: =SUMPRODUCT((Artikelstamm!$AJ$3:$AJ$729="bezahlt")*Artikelstamm!$N$3:$N$729*Artikelstamm!$AE$3:$AE$729)
A18: noch offen | B18: =B14-B17
A20: To-do
A21: Rechnungen noch zu schreiben | B21: =COUNTIFS(Artikelstamm!$Z$3:$Z$729,"*verkauft",Artikelstamm!$AI$3:$AI$729,"")
A22: Rechnungen offen (unbezahlt) | B22: =COUNTIFS(Artikelstamm!$Z$3:$Z$729,"*verkauft",Artikelstamm!$AJ$3:$AJ$729,"offen")
A23: Reservierungen ohne Abholtermin | B23: =COUNTIFS(Artikelstamm!$Z$3:$Z$729,"reserviert",Artikelstamm!$AL$3:$AL$729,"")
A24: Artikel ohne Preis | B24: =COUNTIFS(Artikelstamm!$S$3:$S$729,"")
A25: Artikel ohne Maßangabe | B25: =COUNTIFS(Artikelstamm!$L$3:$L$729,"")
A28: Nach Wertklasse
A29: Wertklasse | B29: Positionen | C29: Umsatz netto | D29: Restwert netto
A30: A | B30: =COUNTIF(Artikelstamm!$J$3:$J$729,$A30) | C30: =SUMPRODUCT((Artikelstamm!$J$3:$J$729=$A30)*Artikelstamm!$N$3:$N$729*Artikelstamm!$AE$3:$AE$729) | D30: =SUMIF(Artikelstamm!$J$3:$J$729,$A30,Artikelstamm!$V$3:$V$729)
A31: B | B31: =COUNTIF(Artikelstamm!$J$3:$J$729,$A31) | C31: =SUMPRODUCT((Artikelstamm!$J$3:$J$729=$A31)*Artikelstamm!$N$3:$N$729*Artikelstamm!$AE$3:$AE$729) | D31: =SUMIF(Artikelstamm!$J$3:$J$729,$A31,Artikelstamm!$V$3:$V$729)
A32: C | B32: =COUNTIF(Artikelstamm!$J$3:$J$729,$A32) | C32: =SUMPRODUCT((Artikelstamm!$J$3:$J$729=$A32)*Artikelstamm!$N$3:$N$729*Artikelstamm!$AE$3:$AE$729) | D32: =SUMIF(Artikelstamm!$J$3:$J$729,$A32,Artikelstamm!$V$3:$V$729)
A33: Summe | B33: =SUM(B30:B32) | C33: =SUM(C30:C32) | D33: =SUM(D30:D32)
A35: Nach Kategorie
A36: Kategorie | B36: Positionen | C36: Umsatz netto | D36: Restwert netto
A37: Büro | B37: =COUNTIF(Artikelstamm!$H$3:$H$729,$A37) | C37: =SUMPRODUCT((Artikelstamm!$H$3:$H$729=$A37)*Artikelstamm!$N$3:$N$729*Artikelstamm!$AE$3:$AE$729) | D37: =SUMIF(Artikelstamm!$H$3:$H$729,$A37,Artikelstamm!$V$3:$V$729)
A38: Deko | B38: =COUNTIF(Artikelstamm!$H$3:$H$729,$A38) | C38: =SUMPRODUCT((Artikelstamm!$H$3:$H$729=$A38)*Artikelstamm!$N$3:$N$729*Artikelstamm!$AE$3:$AE$729) | D38: =SUMIF(Artikelstamm!$H$3:$H$729,$A38,Artikelstamm!$V$3:$V$729)
A39: Garten | B39: =COUNTIF(Artikelstamm!$H$3:$H$729,$A39) | C39: =SUMPRODUCT((Artikelstamm!$H$3:$H$729=$A39)*Artikelstamm!$N$3:$N$729*Artikelstamm!$AE$3:$AE$729) | D39: =SUMIF(Artikelstamm!$H$3:$H$729,$A39,Artikelstamm!$V$3:$V$729)
A40: Kita-Ausstattung | B40: =COUNTIF(Artikelstamm!$H$3:$H$729,$A40) | C40: =SUMPRODUCT((Artikelstamm!$H$3:$H$729=$A40)*Artikelstamm!$N$3:$N$729*Artikelstamm!$AE$3:$AE$729) | D40: =SUMIF(Artikelstamm!$H$3:$H$729,$A40,Artikelstamm!$V$3:$V$729)
A41: Kunst | B41: =COUNTIF(Artikelstamm!$H$3:$H$729,$A41) | C41: =SUMPRODUCT((Artikelstamm!$H$3:$H$729=$A41)*Artikelstamm!$N$3:$N$729*Artikelstamm!$AE$3:$AE$729) | D41: =SUMIF(Artikelstamm!$H$3:$H$729,$A41,Artikelstamm!$V$3:$V$729)
A42: Küchentechnik | B42: =COUNTIF(Artikelstamm!$H$3:$H$729,$A42) | C42: =SUMPRODUCT((Artikelstamm!$H$3:$H$729=$A42)*Artikelstamm!$N$3:$N$729*Artikelstamm!$AE$3:$AE$729) | D42: =SUMIF(Artikelstamm!$H$3:$H$729,$A42,Artikelstamm!$V$3:$V$729)
A43: Leuchten | B43: =COUNTIF(Artikelstamm!$H$3:$H$729,$A43) | C43: =SUMPRODUCT((Artikelstamm!$H$3:$H$729=$A43)*Artikelstamm!$N$3:$N$729*Artikelstamm!$AE$3:$AE$729) | D43: =SUMIF(Artikelstamm!$H$3:$H$729,$A43,Artikelstamm!$V$3:$V$729)
A44: Möbel | B44: =COUNTIF(Artikelstamm!$H$3:$H$729,$A44) | C44: =SUMPRODUCT((Artikelstamm!$H$3:$H$729=$A44)*Artikelstamm!$N$3:$N$729*Artikelstamm!$AE$3:$AE$729) | D44: =SUMIF(Artikelstamm!$H$3:$H$729,$A44,Artikelstamm!$V$3:$V$729)
A45: Pflanzen | B45: =COUNTIF(Artikelstamm!$H$3:$H$729,$A45) | C45: =SUMPRODUCT((Artikelstamm!$H$3:$H$729=$A45)*Artikelstamm!$N$3:$N$729*Artikelstamm!$AE$3:$AE$729) | D45: =SUMIF(Artikelstamm!$H$3:$H$729,$A45,Artikelstamm!$V$3:$V$729)
A46: Sonstiges | B46: =COUNTIF(Artikelstamm!$H$3:$H$729,$A46) | C46: =SUMPRODUCT((Artikelstamm!$H$3:$H$729=$A46)*Artikelstamm!$N$3:$N$729*Artikelstamm!$AE$3:$AE$729) | D46: =SUMIF(Artikelstamm!$H$3:$H$729,$A46,Artikelstamm!$V$3:$V$729)
A47: Spielzeug | B47: =COUNTIF(Artikelstamm!$H$3:$H$729,$A47) | C47: =SUMPRODUCT((Artikelstamm!$H$3:$H$729=$A47)*Artikelstamm!$N$3:$N$729*Artikelstamm!$AE$3:$AE$729) | D47: =SUMIF(Artikelstamm!$H$3:$H$729,$A47,Artikelstamm!$V$3:$V$729)
A48: Technik | B48: =COUNTIF(Artikelstamm!$H$3:$H$729,$A48) | C48: =SUMPRODUCT((Artikelstamm!$H$3:$H$729=$A48)*Artikelstamm!$N$3:$N$729*Artikelstamm!$AE$3:$AE$729) | D48: =SUMIF(Artikelstamm!$H$3:$H$729,$A48,Artikelstamm!$V$3:$V$729)
... A52: zu verschenken | B52: =COUNTIF(Artikelstamm!$H$3:$H$729,$A52) | C52: =SUMPRODUCT((Artikelstamm!$H$3:$H$729=$A52)*Artikelstamm!$N$3:$N$729*Artikelstamm!$AE$3:$AE$729) | D52: =SUMIF(Artikelstamm!$H$3:$H$729,$A52,Artikelstamm!$V$3:$V$729)
A53: Summe | B53: =SUM(B37:B52) | C53: =SUM(C37:C52) | D53: =SUM(D37:D52)
A55: Nach Raum
A56: Raum | B56: Positionen | C56: Umsatz netto | D56: Restwert netto
A57: Abstellraum | B57: =COUNTIF(Artikelstamm!$D$3:$D$729,$A57) | C57: =SUMPRODUCT((Artikelstamm!$D$3:$D$729=$A57)*Artikelstamm!$N$3:$N$729*Artikelstamm!$AE$3:$AE$729) | D57: =SUMIF(Artikelstamm!$D$3:$D$729,$A57,Artikelstamm!$V$3:$V$729)
A58: Atelier | B58: =COUNTIF(Artikelstamm!$D$3:$D$729,$A58) | C58: =SUMPRODUCT((Artikelstamm!$D$3:$D$729=$A58)*Artikelstamm!$N$3:$N$729*Artikelstamm!$AE$3:$AE$729) | D58: =SUMIF(Artikelstamm!$D$3:$D$729,$A58,Artikelstamm!$V$3:$V$729)
A59: Büro | B59: =COUNTIF(Artikelstamm!$D$3:$D$729,$A59) | C59: =SUMPRODUCT((Artikelstamm!$D$3:$D$729=$A59)*Artikelstamm!$N$3:$N$729*Artikelstamm!$AE$3:$AE$729) | D59: =SUMIF(Artikelstamm!$D$3:$D$729,$A59,Artikelstamm!$V$3:$V$729)
A60: Büro und Besprechung | B60: =COUNTIF(Artikelstamm!$D$3:$D$729,$A60) | C60: =SUMPRODUCT((Artikelstamm!$D$3:$D$729=$A60)*Artikelstamm!$N$3:$N$729*Artikelstamm!$AE$3:$AE$729) | D60: =SUMIF(Artikelstamm!$D$3:$D$729,$A60,Artikelstamm!$V$3:$V$729)
A61: Dachterrasse | B61: =COUNTIF(Artikelstamm!$D$3:$D$729,$A61) | C61: =SUMPRODUCT((Artikelstamm!$D$3:$D$729=$A61)*Artikelstamm!$N$3:$N$729*Artikelstamm!$AE$3:$AE$729) | D61: =SUMIF(Artikelstamm!$D$3:$D$729,$A61,Artikelstamm!$V$3:$V$729)
A62: Eingang und Elternlounge | B62: =COUNTIF(Artikelstamm!$D$3:$D$729,$A62) | C62: =SUMPRODUCT((Artikelstamm!$D$3:$D$729=$A62)*Artikelstamm!$N$3:$N$729*Artikelstamm!$AE$3:$AE$729) | D62: =SUMIF(Artikelstamm!$D$3:$D$729,$A62,Artikelstamm!$V$3:$V$729)
A63: Flur | B63: =COUNTIF(Artikelstamm!$D$3:$D$729,$A63) | C63: =SUMPRODUCT((Artikelstamm!$D$3:$D$729=$A63)*Artikelstamm!$N$3:$N$729*Artikelstamm!$AE$3:$AE$729) | D63: =SUMIF(Artikelstamm!$D$3:$D$729,$A63,Artikelstamm!$V$3:$V$729)
A64: Galerie | B64: =COUNTIF(Artikelstamm!$D$3:$D$729,$A64) | C64: =SUMPRODUCT((Artikelstamm!$D$3:$D$729=$A64)*Artikelstamm!$N$3:$N$729*Artikelstamm!$AE$3:$AE$729) | D64: =SUMIF(Artikelstamm!$D$3:$D$729,$A64,Artikelstamm!$V$3:$V$729)
A65: Garderobenflur | B65: =COUNTIF(Artikelstamm!$D$3:$D$729,$A65) | C65: =SUMPRODUCT((Artikelstamm!$D$3:$D$729=$A65)*Artikelstamm!$N$3:$N$729*Artikelstamm!$AE$3:$AE$729) | D65: =SUMIF(Artikelstamm!$D$3:$D$729,$A65,Artikelstamm!$V$3:$V$729)
A66: Garten | B66: =COUNTIF(Artikelstamm!$D$3:$D$729,$A66) | C66: =SUMPRODUCT((Artikelstamm!$D$3:$D$729=$A66)*Artikelstamm!$N$3:$N$729*Artikelstamm!$AE$3:$AE$729) | D66: =SUMIF(Artikelstamm!$D$3:$D$729,$A66,Artikelstamm!$V$3:$V$729)
A67: Gruppenraum | B67: =COUNTIF(Artikelstamm!$D$3:$D$729,$A67) | C67: =SUMPRODUCT((Artikelstamm!$D$3:$D$729=$A67)*Artikelstamm!$N$3:$N$729*Artikelstamm!$AE$3:$AE$729) | D67: =SUMIF(Artikelstamm!$D$3:$D$729,$A67,Artikelstamm!$V$3:$V$729)
A68: Heizung | B68: =COUNTIF(Artikelstamm!$D$3:$D$729,$A68) | C68: =SUMPRODUCT((Artikelstamm!$D$3:$D$729=$A68)*Artikelstamm!$N$3:$N$729*Artikelstamm!$AE$3:$AE$729) | D68: =SUMIF(Artikelstamm!$D$3:$D$729,$A68,Artikelstamm!$V$3:$V$729)
... A84: Werkraum | B84: =COUNTIF(Artikelstamm!$D$3:$D$729,$A84) | C84: =SUMPRODUCT((Artikelstamm!$D$3:$D$729=$A84)*Artikelstamm!$N$3:$N$729*Artikelstamm!$AE$3:$AE$729) | D84: =SUMIF(Artikelstamm!$D$3:$D$729,$A84,Artikelstamm!$V$3:$V$729)
A85: Summe | B85: =SUM(B57:B84) | C85: =SUM(C57:C84) | D85: =SUM(D57:D84)
A87: Nach Verkaufskanal
A88: Verkaufskanal | B88: Positionen | C88: Umsatz netto
A89: Webkatalog | B89: =COUNTIF(Artikelstamm!$AC$3:$AC$729,$A89) | C89: =SUMPRODUCT((Artikelstamm!$AC$3:$AC$729=$A89)*Artikelstamm!$N$3:$N$729*Artikelstamm!$AE$3:$AE$729)
A90: Kleinanzeigen | B90: =COUNTIF(Artikelstamm!$AC$3:$AC$729,$A90) | C90: =SUMPRODUCT((Artikelstamm!$AC$3:$AC$729=$A90)*Artikelstamm!$N$3:$N$729*Artikelstamm!$AE$3:$AE$729)
A91: eBay | B91: =COUNTIF(Artikelstamm!$AC$3:$AC$729,$A91) | C91: =SUMPRODUCT((Artikelstamm!$AC$3:$AC$729=$A91)*Artikelstamm!$N$3:$N$729*Artikelstamm!$AE$3:$AE$729)
A92: Direkt | B92: =COUNTIF(Artikelstamm!$AC$3:$AC$729,$A92) | C92: =SUMPRODUCT((Artikelstamm!$AC$3:$AC$729=$A92)*Artikelstamm!$N$3:$N$729*Artikelstamm!$AE$3:$AE$729)
A93: Händler | B93: =COUNTIF(Artikelstamm!$AC$3:$AC$729,$A93) | C93: =SUMPRODUCT((Artikelstamm!$AC$3:$AC$729=$A93)*Artikelstamm!$N$3:$N$729*Artikelstamm!$AE$3:$AE$729)
A94: Verkaufstag | B94: =COUNTIF(Artikelstamm!$AC$3:$AC$729,$A94) | C94: =SUMPRODUCT((Artikelstamm!$AC$3:$AC$729=$A94)*Artikelstamm!$N$3:$N$729*Artikelstamm!$AE$3:$AE$729)
A95: Summe | B95: =SUM(B89:B94) | C95: =SUM(C89:C94)

Sheet Kasse
A1: Kassenbuch Barverkäufe
A2: Pflicht bei einer GmbH (GoBD): jede Bareinnahme am selben Tag erfassen. Am Verkaufstag reicht eine Sammelzeile mit der Tageseinnahme, dazu ein Zählprotokoll aufbewahren. Bitte einmal mit dem Steuerberater abstimmen, in welcher Form er die Daten haben will.
A4: Datum | B4: Beleg-Nr | C4: Vorgang / Käufer | D4: Einnahme | E4: USt (steuerfrei) | F4: Betrag | G4: Ausgabe | H4: Kassenbestand
C5: Anfangsbestand Kasse | H5: 0
A6: 46308 | B6: 4000117 | C6: Jonathan Kleinknecht | D6: 100 | E6: =IF(D6="","",D6-D6/1.0) | F6: =IF(D6="","",D6/1.0) | H6: =H5+IF(D6="",0,D6)-IF(G6="",0,G6)
A7: 46308 | B7: 4000118 | C7: Aljona Dura | D7: 465 | E7: =IF(D7="","",D7-D7/1.0) | F7: =IF(D7="","",D7/1.0) | H7: =H6+IF(D7="",0,D7)-IF(G7="",0,G7)
A8: 46310 | B8: 4000129 | C8: Tanja Fischer | D8: 70 | E8: =IF(D8="","",D8-D8/1.0) | F8: =IF(D8="","",D8/1.0) | H8: =H7+IF(D8="",0,D8)-IF(G8="",0,G8)
A9: 46312 | B9: 4000136 | C9: Daniela Hauser | D9: 100 | E9: =IF(D9="","",D9-D9/1.0) | F9: =IF(D9="","",D9/1.0) | H9: =H8+IF(D9="",0,D9)-IF(G9="",0,G9)
A10: 46314 | B10: 4000137 | C10: Aljona Dura | D10: 150 | E10: =IF(D10="","",D10-D10/1.0) | F10: =IF(D10="","",D10/1.0) | H10: =H9+IF(D10="",0,D10)-IF(G10="",0,G10)
A11: 46314 | B11: 4000126 | C11: Jessica Lücke | D11: 90 | E11: =IF(D11="","",D11-D11/1.0) | F11: =IF(D11="","",D11/1.0) | H11: =H10+IF(D11="",0,D11)-IF(G11="",0,G11)
A12: 46314 | B12: 4000147 | C12: Lars Hindelang | D12: 50 | E12: =IF(D12="","",D12-D12/1.0) | F12: =IF(D12="","",D12/1.0) | H12: =H11+IF(D12="",0,D12)-IF(G12="",0,G12)
E13: =IF(D13="","",D13-D13/1.0) | F13: =IF(D13="","",D13/1.0) | H13: =H12+IF(D13="",0,D13)-IF(G13="",0,G13)
E14: =IF(D14="","",D14-D14/1.0) | F14: =IF(D14="","",D14/1.0) | H14: =H13+IF(D14="",0,D14)-IF(G14="",0,G14)
E15: =IF(D15="","",D15-D15/1.0) | F15: =IF(D15="","",D15/1.0) | H15: =H14+IF(D15="",0,D15)-IF(G15="",0,G15)
E16: =IF(D16="","",D16-D16/1.0) | F16: =IF(D16="","",D16/1.0) | H16: =H15+IF(D16="",0,D16)-IF(G16="",0,G16)
E17: =IF(D17="","",D17-D17/1.0) | F17: =IF(D17="","",D17/1.0) | H17: =H16+IF(D17="",0,D17)-IF(G17="",0,G17)
E18: =IF(D18="","",D18-D18/1.0) | F18: =IF(D18="","",D18/1.0) | H18: =H17+IF(D18="",0,D18)-IF(G18="",0,G18)
E19: =IF(D19="","",D19-D19/1.0) | F19: =IF(D19="","",D19/1.0) | H19: =H18+IF(D19="",0,D19)-IF(G19="",0,G19)
E20: =IF(D20="","",D20-D20/1.0) | F20: =IF(D20="","",D20/1.0) | H20: =H19+IF(D20="",0,D20)-IF(G20="",0,G20)
E21: =IF(D21="","",D21-D21/1.0) | F21: =IF(D21="","",D21/1.0) | H21: =H20+IF(D21="",0,D21)-IF(G21="",0,G21)
E22: =IF(D22="","",D22-D22/1.0) | F22: =IF(D22="","",D22/1.0) | H22: =H21+IF(D22="",0,D22)-IF(G22="",0,G22)
E23: =IF(D23="","",D23-D23/1.0) | F23: =IF(D23="","",D23/1.0) | H23: =H22+IF(D23="",0,D23)-IF(G23="",0,G23)
E24: =IF(D24="","",D24-D24/1.0) | F24: =IF(D24="","",D24/1.0) | H24: =H23+IF(D24="",0,D24)-IF(G24="",0,G24)
... E55: =IF(D55="","",D55-D55/1.0) | F55: =IF(D55="","",D55/1.0) | H55: =H54+IF(D55="",0,D55)-IF(G55="",0,G55)

Sheet Design
A1: Design und Stammdaten
A2: Hier ändern – nicht in den anderen Blättern. Farben als HEX ohne Raute (z. B. C8102E). Die Werte werden beim Rückeinlesen übernommen und gelten dann für Angebot, Katalog und Webkatalog.
A4: Schlüssel | B4: Wert | C4: Hinweis
A5: Firma | B5: Kikripp GmbH | C5: Vollständige Firmierung, erscheint in Kopf und Fuß aller Dokumente
A6: Strasse | B6: Hermann-Schwer-Str. 1
A7: PLZ_Ort | B7: 78048 Villingen-Schwenningen
A8: Ansprechpartner | B8: Jenny Preisigke
A9: Telefon | B9: 07725 5179702 | C9: Schreibweise bitte prüfen
A10: Email | B10: saldi4kids@outlook.com
A11: Empfaenger_Firma | B11: Mediclin Königsfeld | C11: Empfänger des Angebots
A12: Empfaenger_Person | B12: Frau Jessica Rose
A13: Angebot_Nr | B13: ANG-2026-0001
A14: Angebot_Datum | B14: 15.09.2026
A15: Angebot_Gueltig_bis | B15: 15.10.2026
A16: USt_Satz_Prozent | B16: 0 | C16: Steuerfreie Lieferung gemäß § 4 Nr. 28 UStG (Entscheidung 05.10.2026) - Preise sind Endpreise
A17: Paketrabatt_Prozent | B17: 15 | C17: Nachlass beim Paketangebot
A18: Katalog_URL | B18: https://www.kikripp.de/katalog | C18: Adresse des Webkatalogs, erscheint im Klinik-Angebot
A19: Katalog_Passwort | C19: Bewusst leer - Passwort gehoert nicht ins Projekt. Vor dem Erzeugen setzen: export KIKRIPP_KATALOG_PW=...
A20: Farbe_Rot | B20: C8102E | C20: Bollenhut-Rot - nur als Akzent verwenden
A21: Farbe_Schwarz | B21: 1A1A1A | C21: Kopfzeilen und Struktur
A22: Farbe_Papier | B22: F7F5F2 | C22: warme Fläche
A23: Farbe_Grau | B23: 6B7280 | C23: Sekundärtext
A24: Farbe_Linie | B24: DCDCDC | C24: feine Linien und Rahmen
A25: Feld_Klinik | B25: E4E4E4 | C25: Ausfüllfelder für die Klinik (mittleres Grau)
A26: Feld_Intern | B26: F2F2F2 | C26: interne Ausfüllfelder (helles Grau)
A27: Zeile_Wechsel | B27: FAFAFA | C27: Zeilenwechsel in Tabellen
A28: Schrift_Excel | B28: Arial
A29: Schrift_Web | B29: Poppins | C29: Google-Font für den Webkatalog, mit Systemschrift als Rückfall
